Workbook

Sheet 📦 Materiales
B1: CUBO · Precios de Materiales — Sismat
A2: Fuente: Sismat · 2026-05-15
A3: ID Sismat | B3: Categoría | C3: Material | D3: Unidad | E3: Precio $
A4: 276 | B4: Aditivos, Impermeabilizaciones y Aislaciones | C4: Aditivo Tacurú Weber. 01lt | D4: Unidad | E4: 19273.89
A5: 277 | B5: Aditivos, Impermeabilizaciones y Aislaciones | C5: Aditivo Tacurú Weber. 04lt | D5: Unidad | E5: 77095.58
A6: 1689 | B6: Aditivos, Impermeabilizaciones y Aislaciones | C6: Aditivo Tacurú Weber. 10lt | D6: Unidad | E6: 115920.41
A7: 1690 | B7: Aditivos, Impermeabilizaciones y Aislaciones | C7: Aditivo Tacurú Weber. 20lt | D7: Unidad | E7: 225294.7
A8: 115 | B8: Aditivos, Impermeabilizaciones y Aislaciones | C8: Aditivos p/H° acelerante de frague Sika 3 (Sin Cloruro) | D8: Litro | E8: 18532.59
A9: 116 | B9: Aditivos, Impermeabilizaciones y Aislaciones | C9: Aditivos p/H° adhesivo y plastificante Sika Latex | D9: Litro | E9: 33358.67
A10: 117 | B10: Aditivos, Impermeabilizaciones y Aislaciones | C10: Aditivos p/H° endurecedor rápido plastificante, Sikacrete | D10: Litro | E10: 6548.19
A11: 118 | B11: Aditivos, Impermeabilizaciones y Aislaciones | C11: Aditivos p/H° Separol Sika, p/ desmolde madera | D11: Litro | E11: 36570.97
A12: 119 | B12: Aditivos, Impermeabilizaciones y Aislaciones | C12: Aditivos p/H° Separol Sika, p/ desmolde metal | D12: Litro | E12: 39041.99
A13: 67 | B13: Aditivos, Impermeabilizaciones y Aislaciones | C13: Aditivos p/H° Sika Antisol normaliz. p/curado de H° | D13: Kilogramo | E13: 10378.28
A14: 120 | B14: Aditivos, Impermeabilizaciones y Aislaciones | C14: Aditivos p/hormigones Sikacim ligante (ex Sika Fix) | D14: Litro | E14: 12355.08
A15: 875 | B15: Aditivos, Impermeabilizaciones y Aislaciones | C15: Aislante Hidrofugo Wichi | D15: Metro cuadrado | E15: 2634.1
... A1392: 9999 | B1392: Consumibles | C1392: LLANA LISA (U) | D1392: Unidad | E1392: 10500
A1393: 9999 | B1393: Consumibles | C1393: CARTÓN CORRUGADO (M2) | D1393: Metro cuadrado | E1393: =13000/25 -> 520
A1394: 9999 | B1394: Aditivos, Impermeabilizaciones y Aislaciones | C1394: MEMBRANA ASFÁLTICA GEOTEXTIL (M2) | D1394: Metro cuadrado | E1394: 8000
A1395: 9999 | B1395: Consumibles | C1395: FRATACHO ABRASIVO (U) | D1395: Unidad | E1395: 4500
A1396: 9999 | B1396: Consumibles | C1396: SEPARADORES PORCELANATOS TIPO CUÑA (U) | D1396: Unidad | E1396: =11400/150 -> 76
A1397: 9999 | B1397: Consumibles | C1397: LLANA DENTADA 10MM (U) | D1397: Unidad | E1397: 12300
A1398: 9999 | B1398: Consumibles | C1398: DISCO DIAMANTADO PARA PORCELANATO (U) | D1398: Unidad | E1398: 24000
A1399: 9999 | B1399: Construcción en Seco y Steel Framing | C1399: FIJACIONES (U) | D1399: Unidad | E1399: =5800/25 -> 232
A1400: 9999 | B1400: Construcción en Seco y Steel Framing | C1400: MEMBRANA HIDROFUGA TIPO TYBEK (M2) | D1400: Metro cuadrado | E1400: =170000/30 -> 5666.6667
A1401: 9999 | B1401: Consumibles | C1401: PINCEL N°20 (U) | D1401: Unidad | E1401: 5000
A1402: 9999 | B1402: Consumibles | C1402: PINCEL N°5 (U) | D1402: Unidad | E1402: 1200

Sheet 🔨 Mano de Obra
A1: CUBO · Precios de Mano de Obra — Sismat
A2: Fuente: Sismat · 2026-05-15
A3: ID Sismat | B3: Categoría | C3: Tarea | D3: Detalle | E3: Unidad | F3: Precio $
A4: 205 | B4: Trabajos Preliminares | C4: Baño químico | D4: Alquiler por mes | E4: Unidad | F4: 0 | H4: =CONCATENATE(B4," ",C4) -> Trabajos Preliminares Baño químico | I4: =F4 -> 0
A5: 107 | B5: Trabajos Preliminares | C5: Cartel de obra | E5: Metro cuadrado | F5: 527065.34 | H5: =CONCATENATE(B5," ",C5) -> Trabajos Preliminares Cartel de obra | I5: =F5 -> 527065.34
A6: 108 | B6: Trabajos Preliminares | C6: Cerco de obra | E6: Metro lineal | F6: 53961.44 | H6: =CONCATENATE(B6," ",C6) -> Trabajos Preliminares Cerco de obra | I6: =F6 -> 53961.44
A7: 117 | B7: Trabajos Preliminares | C7: Contenedor chico | D7: Alquiler por unidad | E7: Unidad | F7: 0 | H7: =CONCATENATE(B7," ",C7) -> Trabajos Preliminares Contenedor chico | I7: =F7 -> 0
A8: 211 | B8: Trabajos Preliminares | C8: Contenedor grande | D8: Alquiler por unidad | E8: Unidad | F8: 0 | H8: =CONCATENATE(B8," ",C8) -> Trabajos Preliminares Contenedor grande | I8: =F8 -> 0
A9: 109 | B9: Trabajos Preliminares | C9: Defensa de protección para trabajo en obra | E9: Metro lineal | F9: 125491.76 | H9: =CONCATENATE(B9," ",C9) -> Trabajos Preliminares Defensa de protección para trabajo en obra | I9: =F9 -> 125491.76
A10: 432 | B10: Trabajos Preliminares | C10: Empalizada 10ml x 2,00m altura | D10: Con Chapa y Perfiles + Portón corredizo manual. (Incluye Materiales) | E10: Unidad | F10: 836098.48 | H10: =CONCATENATE(B10," ",C10) -> Trabajos Preliminares Empalizada 10ml x 2,00m altura | I10: =F10 -> 836098.48
A11: 258 | B11: Trabajos Preliminares | C11: Limpieza de terreno | D11: Desmalezar + corte de pasto | E11: Metro cuadrado | F11: 11294.28 | H11: =CONCATENATE(B11," ",C11) -> Trabajos Preliminares Limpieza de terreno | I11: =F11 -> 11294.28
A12: 104 | B12: Trabajos Preliminares | C12: Limpieza y nivelación de terreno. | E12: Metro cuadrado | F12: 26604.23 | H12: =CONCATENATE(B12," ",C12) -> Trabajos Preliminares Limpieza y nivelación de terreno. | I12: =F12 -> 26604.23
A13: 369 | B13: Trabajos Preliminares | C13: Obrador (1,80 x 2,40 mts) | D13: Alquiler por mes | E13: Unidad | F13: 0 | H13: =CONCATENATE(B13," ",C13) -> Trabajos Preliminares Obrador (1,80 x 2,40 mts) | I13: =F13 -> 0
A14: 105 | B14: Trabajos Preliminares | C14: Obrador, depósito y sanitario | E14: Metro cuadrado | F14: 238434.33 | H14: =CONCATENATE(B14," ",C14) -> Trabajos Preliminares Obrador, depósito y sanitario | I14: =F14 -> 238434.33
A15: 14 | B15: Trabajos Preliminares | C15: Obrador, Replanteo y Nivelación | D15: Vivienda h/80m², incluye estacas, tirar escuadras y fijar niveles | E15: Global | F15: 953737.26 | H15: =CONCATENATE(B15," ",C15) -> Trabajos Preliminares Obrador, Replanteo y Nivelación | I15: =F15 -> 953737.26
A16: 156 | B16: Trabajos Preliminares | C16: Pilar de luz tradicional | E16: Unidad | F16: 376475.25 | H16: =CONCATENATE(B16," ",C16) -> Trabajos Preliminares Pilar de luz tradicional | I16: =F16 -> 376475.25
A17: 106 | B17: Trabajos Preliminares | C17: Replanteo | E17: Metro cuadrado | F17: 3513.76 | H17: =CONCATENATE(B17," ",C17) -> Trabajos Preliminares Replanteo | I17: =F17 -> 3513.76
A18: 237 | B18: Trabajos Preliminares | C18: Retiro de tierra y nivelación de sup. p/ejecutar contrapisos y/o plateas. Incluye compactacion | E18: Metro cuadrado | F18: 20078.66 | H18: =CONCATENATE(B18," ",C18) -> Trabajos Preliminares Retiro de tierra y nivelación de sup. p/ejecutar contrapisos y/o plateas. Incluye compactacion | I18: =F18 -> 20078.66
A19: 113 | B19: Demoliciones | C19: De contrapisos | E19: Metro cuadrado | F19: 57578.59 | H19: =CONCATENATE(B19," ",C19) -> Demoliciones De contrapisos | I19: =F19 -> 57578.59
A20: 110 | B20: Demoliciones | C20: De estructura de hormigón | E20: Metro cùbico | F20: 463827.32 | H20: =CONCATENATE(B20," ",C20) -> Demoliciones De estructura de hormigón | I20: =F20 -> 463827.32
A21: 111 | B21: Demoliciones | C21: De mamposterías | E21: Metro cùbico | F21: 268207.84 | H21: =CONCATENATE(B21," ",C21) -> Demoliciones De mamposterías | I21: =F21*0.15 -> 40231.176
A22: 112 | B22: Demoliciones | C22: De pisos | E22: Metro cuadrado | F22: 33218.38 | H22: =CONCATENATE(B22," ",C22) -> Demoliciones De pisos | I22: =F22 -> 33218.38
A23: 263 | B23: Demoliciones | C23: De techos (Chapas y Tejas) | E23: Metro cuadrado | F23: 24606.24 | H23: =CONCATENATE(B23," ",C23) -> Demoliciones De techos (Chapas y Tejas) | I23: =F23 -> 24606.24
A24: 116 | B24: Demoliciones | C24: Demolición obra completa | E24: Metro cuadrado | F24: 1476373.4 | H24: =CONCATENATE(B24," ",C24) -> Demoliciones Demolición obra completa | I24: =F24 -> 1476373.4
A25: 115 | B25: Demoliciones | C25: Picado de revestimiento | E25: Metro cuadrado | F25: 31742.08 | H25: =CONCATENATE(B25," ",C25) -> Demoliciones Picado de revestimiento | I25: =F25 -> 31742.08
A26: 114 | B26: Demoliciones | C26: Picado de revoques | E26: Metro cuadrado | F26: 41830.57 | H26: =CONCATENATE(B26," ",C26) -> Demoliciones Picado de revoques | I26: =F26 -> 41830.57
A27: 118 | B27: Demoliciones | C27: Retiro de membrana existente | E27: Metro cuadrado | F27: 12549.17 | H27: =CONCATENATE(B27," ",C27) -> Demoliciones Retiro de membrana existente | I27: =F27 -> 12549.17
A28: 122 | B28: Movimiento de suelos | C28: Carga y retiro de tierra con camión | E28: Metro cùbico | F28: 41412.3 | H28: =CONCATENATE(B28," ",C28) -> Movimiento de suelos Carga y retiro de tierra con camión | I28: =F28 -> 41412.3
A29: 16 | B29: Movimiento de suelos | C29: Construcción aro perimetral de mampostería y losa para pozo ciego. | D29: Losa de cierre y colocación caño de ventilación. | E29: Unidad | F29: 301180.17 | H29: =CONCATENATE(B29," ",C29) -> Movimiento de suelos Construcción aro perimetral de mampostería y losa para pozo ciego. | I29: =F29 -> 301180.17
A30: 121 | B30: Movimiento de suelos | C30: Destape del terreno (hasta 20/30cm de prof. con pala frontal) | E30: Metro cùbico | F30: 96628.67 | H30: =CONCATENATE(B30," ",C30) -> Movimiento de suelos Destape del terreno (hasta 20/30cm de prof. con pala frontal) | I30: =F30 -> 96628.67
A31: 18 | B31: Movimiento de suelos | C31: Excavación de bases | E31: Metro cùbico | F31: 52706.55 | H31: =CONCATENATE(B31," ",C31) -> Movimiento de suelos Excavación de bases | I31: =F31 -> 52706.55
A32: 119 | B32: Movimiento de suelos | C32: Excavación de pozos para pilotín (diam. 20cm - prof. 1.50m) | E32: Unidad | F32: 16313.91 | H32: =CONCATENATE(B32," ",C32) -> Movimiento de suelos Excavación de pozos para pilotín (diam. 20cm - prof. 1.50m) | I32: =F32 -> 16313.91
A33: 120 | B33: Movimiento de suelos | C33: Excavación de sótano a máquina | E33: Metro cùbico | F33: 60236.01 | H33: =CONCATENATE(B33," ",C33) -> Movimiento de suelos Excavación de sótano a máquina | I33: =F33 -> 60236.01
A34: 17 | B34: Movimiento de suelos | C34: Excavación de vigas de fundición | E34: Metro cùbico | F34: 52706.55 | H34: =CONCATENATE(B34," ",C34) -> Movimiento de suelos Excavación de vigas de fundición | I34: =F34 -> 52706.55
A35: 15 | B35: Movimiento de suelos | C35: Excavación p/pozo ciego (diámetro 1,60ml) | E35: Metro cùbico | F35: 71530.32 | H35: =CONCATENATE(B35," ",C35) -> Movimiento de suelos Excavación p/pozo ciego (diámetro 1,60ml) | I35: =F35 -> 71530.32
A36: 212 | B36: Movimiento de suelos | C36: Relleno de suelos con tierra fértil (para Jardín) | E36: Metro cùbico | F36: 30118.05 | H36: =CONCATENATE(B36," ",C36) -> Movimiento de suelos Relleno de suelos con tierra fértil (para Jardín) | I36: =F36 -> 30118.05
A37: 167 | B37: Movimiento de suelos | C37: Relleno de suelos con tosca (para nivelar) | E37: Metro cùbico | F37: 22588.49 | H37: =CONCATENATE(B37," ",C37) -> Movimiento de suelos Relleno de suelos con tosca (para nivelar) | I37: =F37 -> 22588.49
A38: 174 | B38: Fundaciones | C38: Base 1 de H°A° 0.60x0.60 (armado y llenado) | E38: Unidad | F38: 62745.9 | H38: =CONCATENATE(B38," ",C38) -> Fundaciones Base 1 de H°A° 0.60x0.60 (armado y llenado) | I38: =F38 -> 62745.9
A39: 175 | B39: Fundaciones | C39: Base 2 de H°A° 0.60x1.00 (armado y llenado) | E39: Unidad | F39: 82824.54 | H39: =CONCATENATE(B39," ",C39) -> Fundaciones Base 2 de H°A° 0.60x1.00 (armado y llenado) | I39: =F39 -> 82824.54
A40: 19 | B40: Fundaciones | C40: Base 3 de H°A° 0.80x0.80 (armado y llenado) | E40: Unidad | F40: 95373.73 | H40: =CONCATENATE(B40," ",C40) -> Fundaciones Base 3 de H°A° 0.80x0.80 (armado y llenado) | I40: =F40 -> 95373.73
A41: 176 | B41: Fundaciones | C41: Base 4 de H°A° 1.00x1.00 (armado y llenado) | E41: Unidad | F41: 115452.41 | H41: =CONCATENATE(B41," ",C41) -> Fundaciones Base 4 de H°A° 1.00x1.00 (armado y llenado) | I41: =F41 -> 115452.41
... A47: 180 | B47: Fundaciones | C47: Platea de H°A° (espesor 25cm.) | E47: Metro cuadrado | F47: 45177.05 | H47: =CONCATENATE(B47," ",C47) -> Fundaciones Platea de H°A° (espesor 25cm.) | I47: =F47 -> 45177.05
A48: 20 | B48: Fundaciones | C48: Viga de fundación 20x25 (armado y llenado) | D48: con 4 hierros del 10. (estribos del 6) | E48: Metro lineal | F48: 30118.05 | H48: =CONCATENATE(B48," ",C48) -> Fundaciones Viga de fundación 20x25 (armado y llenado) | I48: =F48 -> 30118.05
A49: 260 | B49: Fundaciones | C49: Viga de fundación 20x30 (armado y llenado) | D49: Con 4 hierros del 10. (estribos del 6) | E49: Metro lineal | F49: 37647.55 | H49: =CONCATENATE(B49," ",C49) -> Fundaciones Viga de fundación 20x30 (armado y llenado) | I49: =F49 -> 37647.55
A50: 442 | B50: Fundaciones | C50: Viga de fundación 25x25 (armado y llenado) | D50: con 4 hierros del 10. (estribos del 6) | E50: Metro lineal | F50: 37647.7 | H50: =CONCATENATE(B50," ",C50) -> Fundaciones Viga de fundación 25x25 (armado y llenado) | I50: =F50 -> 37647.7
A51: 177 | B51: Fundaciones | C51: Viga de fundación 25x30 (armado y llenado) | D51: con 4 hierros del 10. (estribos del 6) | E51: Metro lineal | F51: 41412.3 | H51: =CONCATENATE(B51," ",C51) -> Fundaciones Viga de fundación 25x30 (armado y llenado) | I51: =F51 -> 41412.3
A52: 443 | B52: Fundaciones | C52: Viga de fundación 30x30 (armado y llenado) | D52: con 4 hierros del 10. (estribos del 6) | E52: Metro lineal | F52: 43293.12 | H52: =CONCATENATE(B52," ",C52) -> Fundaciones Viga de fundación 30x30 (armado y llenado) | I52: =F52 -> 43293.12
A53: 190 | B53: Fundaciones | C53: Zapata de Hormigón Pobre (0.40x0.80) | E53: Metro lineal | F53: 37647.55 | H53: =CONCATENATE(B53," ",C53) -> Fundaciones Zapata de Hormigón Pobre (0.40x0.80) | I53: =F53 -> 37647.55
A54: 22 | B54: Mampostería de cimientos | C54: Mampostería de 15 | D54: ladrillo común | E54: Metro cuadrado | F54: 19768.66 | H54: =CONCATENATE(B54," ",C54) -> Mampostería de cimientos Mampostería de 15 | I54: =F54 -> 19768.66
A55: 295 | B55: Mampostería de cimientos | C55: Mampostería de 15 (con cemento de albañilería) | E55: Metro cuadrado | F55: 19768.66 | H55: =CONCATENATE(B55," ",C55) -> Mampostería de cimientos Mampostería de 15 (con cemento de albañilería) | I55: =F55 -> 19768.66
A56: 183 | B56: Mampostería de cimientos | C56: Mampostería de 20 | D56: ladrillo común | E56: Metro cuadrado | F56: 24330.63 | H56: =CONCATENATE(B56," ",C56) -> Mampostería de cimientos Mampostería de 20 | I56: =F56 -> 24330.63
A57: 296 | B57: Mampostería de cimientos | C57: Mampostería de 20 (con cemento de albañilería) | E57: Metro cuadrado | F57: 24330.63 | H57: =CONCATENATE(B57," ",C57) -> Mampostería de cimientos Mampostería de 20 (con cemento de albañilería) | I57: =F57 -> 24330.63
A58: 21 | B58: Mampostería de cimientos | C58: Mampostería de 30 | D58: ladrillo común | E58: Metro cuadrado | F58: 32694.35 | H58: =CONCATENATE(B58," ",C58) -> Mampostería de cimientos Mampostería de 30 | I58: =F58 -> 32694.35
A59: 297 | B59: Mampostería de cimientos | C59: Mampostería de 30 (con cemento de albañilería) | E59: Metro cuadrado | F59: 32694.35 | H59: =CONCATENATE(B59," ",C59) -> Mampostería de cimientos Mampostería de 30 (con cemento de albañilería) | I59: =F59 -> 32694.35
A60: 23 | B60: Capas aisladoras | C60: Horizontal (Espesor 2cm) | D60: incluye hidrofugo y pintura asfáltica | E60: Metro cuadrado | F60: 14468.45 | H60: =CONCATENATE(B60," ",C60) -> Capas aisladoras Horizontal (Espesor 2cm) | I60: =F60 -> 14468.45
A61: 24 | B61: Capas aisladoras | C61: Vertical azotado (Espesor 0.5cm) | D61: incluye hidrofugo y pintura asfáltica | E61: Metro cuadrado | F61: 12918.28 | H61: =CONCATENATE(B61," ",C61) -> Capas aisladoras Vertical azotado (Espesor 0.5cm) | I61: =F61 -> 12918.28
A62: 32 | B62: Mampostería de elevación con cemento tradicional | C62: Bloque Hormigón Liso 09x19x39 | E62: Metro cuadrado | F62: 16727.31 | H62: =CONCATENATE(B62," ",C62) -> Mampostería de elevación con cemento tradicional Bloque Hormigón Liso 09x19x39 | I62: =F62 -> 16727.31
A63: 33 | B63: Mampostería de elevación con cemento tradicional | C63: Bloque Hormigón Liso 19x19x39 | E63: Metro cuadrado | F63: 22809.94 | H63: =CONCATENATE(B63," ",C63) -> Mampostería de elevación con cemento tradicional Bloque Hormigón Liso 19x19x39 | I63: =F63 -> 22809.94
A64: 184 | B64: Mampostería de elevación con cemento tradicional | C64: Bloque Hormigón Símil Piedra 12,5x19x39 | E64: Metro cuadrado | F64: 20022.08 | H64: =CONCATENATE(B64," ",C64) -> Mampostería de elevación con cemento tradicional Bloque Hormigón Símil Piedra 12,5x19x39 | I64: =F64 -> 20022.08
A65: 185 | B65: Mampostería de elevación con cemento tradicional | C65: Bloque Hormigón Símil Piedra 19x19x39 | E65: Metro cuadrado | F65: 24837.5 | H65: =CONCATENATE(B65," ",C65) -> Mampostería de elevación con cemento tradicional Bloque Hormigón Símil Piedra 19x19x39 | I65: =F65 -> 24837.5
A66: 25 | B66: Mampostería de elevación con cemento tradicional | C66: Ladrillo común de 15 | E66: Metro cuadrado | F66: 19768.66 | H66: =CONCATENATE(B66," ",C66) -> Mampostería de elevación con cemento tradicional Ladrillo común de 15 | I66: =F66 -> 19768.66
A67: 213 | B67: Mampostería de elevación con cemento tradicional | C67: Ladrillo común de 20 | E67: Metro cuadrado | F67: 24330.63 | H67: =CONCATENATE(B67," ",C67) -> Mampostería de elevación con cemento tradicional Ladrillo común de 20 | I67: =F67 -> 24330.63
A68: 26 | B68: Mampostería de elevación con cemento tradicional | C68: Ladrillo común de 30 | E68: Metro cuadrado | F68: 32694.35 | H68: =CONCATENATE(B68," ",C68) -> Mampostería de elevación con cemento tradicional Ladrillo común de 30 | I68: =F68 -> 32694.35
A69: 58 | B69: Mampostería de elevación con cemento tradicional | C69: Ladrillo común visto de 15cm | D69: con junta tomada | E69: Metro cuadrado | F69: 29146.05 | H69: =CONCATENATE(B69," ",C69) -> Mampostería de elevación con cemento tradicional Ladrillo común visto de 15cm | I69: =F69 -> 29146.05
A70: 30 | B70: Mampostería de elevación con cemento tradicional | C70: Ladrillo portante 12x19x33 | E70: Metro cuadrado | F70: 21796.2 | H70: =CONCATENATE(B70," ",C70) -> Mampostería de elevación con cemento tradicional Ladrillo portante 12x19x33 | I70: =F70 -> 21796.2
A71: 31 | B71: Mampostería de elevación con cemento tradicional | C71: Ladrillo portante 18x19x33 | E71: Metro cuadrado | F71: 23823.73 | H71: =CONCATENATE(B71," ",C71) -> Mampostería de elevación con cemento tradicional Ladrillo portante 18x19x33 | I71: =F71 -> 23823.73
A72: 27 | B72: Mampostería de elevación con cemento tradicional | C72: Ladrillos huecos 08x18x33 | E72: Metro cuadrado | F72: 14953.21 | H72: =CONCATENATE(B72," ",C72) -> Mampostería de elevación con cemento tradicional Ladrillos huecos 08x18x33 | I72: =F72 -> 14953.21
A73: 28 | B73: Mampostería de elevación con cemento tradicional | C73: Ladrillos huecos 12x18x33 | E73: Metro cuadrado | F73: 18247.95 | H73: =CONCATENATE(B73," ",C73) -> Mampostería de elevación con cemento tradicional Ladrillos huecos 12x18x33 | I73: =F73 -> 18247.95
A74: 29 | B74: Mampostería de elevación con cemento tradicional | C74: Ladrillos huecos 18x18x33 | E74: Metro cuadrado | F74: 21542.73 | H74: =CONCATENATE(B74," ",C74) -> Mampostería de elevación con cemento tradicional Ladrillos huecos 18x18x33 | I74: =F74 -> 21542.73
A75: 266 | B75: Mampostería de elevación con cemento tradicional | C75: Ladrillos huecos para encadenados 12x18x33 | D75: Incluye Hormigón Armado c/ 4 barras del 8 y estribos del 4,2 | E75: Metro lineal | F75: 16473.86 | H75: =CONCATENATE(B75," ",C75) -> Mampostería de elevación con cemento tradicional Ladrillos huecos para encadenados 12x18x33 | I75: =F75 -> 16473.86
A76: 267 | B76: Mampostería de elevación con cemento tradicional | C76: Ladrillos huecos para encadenados 18x18x33 | D76: Incluye Hormigón Armado c/ 4 barras del 8 y estribos del 4,2 | E76: Metro lineal | F76: 17741.09 | H76: =CONCATENATE(B76," ",C76) -> Mampostería de elevación con cemento tradicional Ladrillos huecos para encadenados 18x18x33 | I76: =F76 -> 17741.09
A77: 239 | B77: Mampostería de elevación con cemento tradicional | C77: Tomado de juntas | E77: Metro cuadrado | F77: 12418.77 | H77: =CONCATENATE(B77," ",C77) -> Mampostería de elevación con cemento tradicional Tomado de juntas | I77: =F77 -> 12418.77
A78: 309 | B78: Mampostería de elevación con cemento de albañilería | C78: Bloque Hormigón Liso 09x19x39 | D78: Con cemento de albañilería | E78: Metro cuadrado | F78: 16727.31 | H78: =CONCATENATE(B78," ",C78) -> Mampostería de elevación con cemento de albañilería Bloque Hormigón Liso 09x19x39 | I78: =F78 -> 16727.31
A79: 310 | B79: Mampostería de elevación con cemento de albañilería | C79: Bloque Hormigón Liso 19x19x39 | D79: Con cemento de albañilería | E79: Metro cuadrado | F79: 22809.94 | H79: =CONCATENATE(B79," ",C79) -> Mampostería de elevación con cemento de albañilería Bloque Hormigón Liso 19x19x39 | I79: =F79 -> 22809.94
A80: 307 | B80: Mampostería de elevación con cemento de albañilería | C80: Bloque Hormigón Símil Piedra 12,5x19x39 | D80: Con cemento de albañilería | E80: Metro cuadrado | F80: 20022.08 | H80: =CONCATENATE(B80," ",C80) -> Mampostería de elevación con cemento de albañilería Bloque Hormigón Símil Piedra 12,5x19x39 | I80: =F80 -> 20022.08
A81: 308 | B81: Mampostería de elevación con cemento de albañilería | C81: Bloque Hormigón Símil Piedra 19x19x39 | D81: Con cemento de albañilería | E81: Metro cuadrado | F81: 24837.5 | H81: =CONCATENATE(B81," ",C81) -> Mampostería de elevación con cemento de albañilería Bloque Hormigón Símil Piedra 19x19x39 | I81: =F81 -> 24837.5
A82: 298 | B82: Mampostería de elevación con cemento de albañilería | C82: Ladrillo común de 15 | D82: Con cemento de albañilería | E82: Metro cuadrado | F82: 19768.66 | H82: =CONCATENATE(B82," ",C82) -> Mampostería de elevación con cemento de albañilería Ladrillo común de 15 | I82: =F82 -> 19768.66
A83: 299 | B83: Mampostería de elevación con cemento de albañilería | C83: Ladrillo común de 20 | D83: Con cemento de albañilería | E83: Metro cuadrado | F83: 24330.63 | H83: =CONCATENATE(B83," ",C83) -> Mampostería de elevación con cemento de albañilería Ladrillo común de 20 | I83: =F83 -> 24330.63
A84: 300 | B84: Mampostería de elevación con cemento de albañilería | C84: Ladrillo común de 30 | D84: Con cemento de albañilería | E84: Metro cuadrado | F84: 32694.35 | H84: =CONCATENATE(B84," ",C84) -> Mampostería de elevación con cemento de albañilería Ladrillo común de 30 | I84: =F84 -> 32694.35
A85: 301 | B85: Mampostería de elevación con cemento de albañilería | C85: Ladrillo común visto de 15cm | D85: Con cemento de albañilería | E85: Metro cuadrado | F85: 29146.05 | H85: =CONCATENATE(B85," ",C85) -> Mampostería de elevación con cemento de albañilería Ladrillo común visto de 15cm | I85: =F85 -> 29146.05
A86: 302 | B86: Mampostería de elevación con cemento de albañilería | C86: Ladrillo portante 12x19x39 | D86: Con cemento de albañilería | E86: Metro cuadrado | F86: 21796.2 | H86: =CONCATENATE(B86," ",C86) -> Mampostería de elevación con cemento de albañilería Ladrillo portante 12x19x39 | I86: =F86 -> 21796.2
A87: 303 | B87: Mampostería de elevación con cemento de albañilería | C87: Ladrillo portante 18x19x39 | D87: Con cemento de albañilería | E87: Metro cuadrado | F87: 23823.73 | H87: =CONCATENATE(B87," ",C87) -> Mampostería de elevación con cemento de albañilería Ladrillo portante 18x19x39 | I87: =F87 -> 23823.73
A88: 304 | B88: Mampostería de elevación con cemento de albañilería | C88: Ladrillos huecos 08x18x33 | D88: Con cemento de albañilería | E88: Metro cuadrado | F88: 14953.21 | H88: =CONCATENATE(B88," ",C88) -> Mampostería de elevación con cemento de albañilería Ladrillos huecos 08x18x33 | I88: =F88 -> 14953.21
A89: 305 | B89: Mampostería de elevación con cemento de albañilería | C89: Ladrillos huecos 12x18x33 | D89: Con cemento de albañilería | E89: Metro cuadrado | F89: 18247.95 | H89: =CONCATENATE(B89," ",C89) -> Mampostería de elevación con cemento de albañilería Ladrillos huecos 12x18x33 | I89: =F89 -> 18247.95
... A93: 204 | B93: Mampostería de elevación con Retak | C93: Ladrillo RETAK ¨U¨ Refuerzo Vertical y/o Horizontal 50x25x20cm. | D93: Incluye armadura y hormigón | E93: Metro lineal | F93: 12165.32 | H93: =CONCATENATE(B93," ",C93) -> Mampostería de elevación con Retak Ladrillo RETAK ¨U¨ Refuerzo Vertical y/o Horizontal 50x25x20cm. | I93: =F93 -> 12165.32
A94: 195 | B94: Mampostería de elevación con Retak | C94: Ladrillo RETAK 50x25x07,5cm. (No portante) | E94: Metro cuadrado | F94: 13432.54 | H94: =CONCATENATE(B94," ",C94) -> Mampostería de elevación con Retak Ladrillo RETAK 50x25x07,5cm. (No portante) | I94: =F94 -> 13432.54
A95: 196 | B95: Mampostería de elevación con Retak | C95: Ladrillo RETAK 50x25x10cm. (No portante) | E95: Metro cuadrado | F95: 14699.74 | H95: =CONCATENATE(B95," ",C95) -> Mampostería de elevación con Retak Ladrillo RETAK 50x25x10cm. (No portante) | I95: =F95 -> 14699.74
A96: 197 | B96: Mampostería de elevación con Retak | C96: Ladrillo RETAK 50x25x12,5cm. (No portante) | E96: Metro cuadrado | F96: 16727.31 | H96: =CONCATENATE(B96," ",C96) -> Mampostería de elevación con Retak Ladrillo RETAK 50x25x12,5cm. (No portante) | I96: =F96 -> 16727.31
A97: 198 | B97: Mampostería de elevación con Retak | C97: Ladrillo RETAK 50x25x15cm. (Portante) | E97: Metro cuadrado | F97: 17994.5 | H97: =CONCATENATE(B97," ",C97) -> Mampostería de elevación con Retak Ladrillo RETAK 50x25x15cm. (Portante) | I97: =F97 -> 17994.5
A98: 199 | B98: Mampostería de elevación con Retak | C98: Ladrillo RETAK 50x25x17,5cm. (Portante) | E98: Metro cuadrado | F98: 20022.08 | H98: =CONCATENATE(B98," ",C98) -> Mampostería de elevación con Retak Ladrillo RETAK 50x25x17,5cm. (Portante) | I98: =F98 -> 20022.08
A99: 200 | B99: Mampostería de elevación con Retak | C99: Ladrillo RETAK 50x25x20cm. (Portante) | E99: Metro cuadrado | F99: 21542.73 | H99: =CONCATENATE(B99," ",C99) -> Mampostería de elevación con Retak Ladrillo RETAK 50x25x20cm. (Portante) | I99: =F99 -> 21542.73
A100: 201 | B100: Mampostería de elevación con Retak | C100: Ladrillo RETAK 50x25x25cm. (Portante) | E100: Metro cuadrado | F100: 23316.83 | H100: =CONCATENATE(B100," ",C100) -> Mampostería de elevación con Retak Ladrillo RETAK 50x25x25cm. (Portante) | I100: =F100 -> 23316.83
A101: 427 | B101: Mampostería de elevación con Rapibrick | C101: Ladrillos Huecos 08x18x33 | E101: Metro cuadrado | F101: 14953.55 | H101: =CONCATENATE(B101," ",C101) -> Mampostería de elevación con Rapibrick Ladrillos Huecos 08x18x33 | I101: =F101 -> 14953.55
A102: 428 | B102: Mampostería de elevación con Rapibrick | C102: Ladrillos Huecos 12x18x33 | E102: Metro cuadrado | F102: 18247.86 | H102: =CONCATENATE(B102," ",C102) -> Mampostería de elevación con Rapibrick Ladrillos Huecos 12x18x33 | I102: =F102 -> 18247.86
A103: 429 | B103: Mampostería de elevación con Rapibrick | C103: Ladrillos Huecos 18x18x33 | E103: Metro cuadrado | F103: 21543.32 | H103: =CONCATENATE(B103," ",C103) -> Mampostería de elevación con Rapibrick Ladrillos Huecos 18x18x33 | I103: =F103 -> 21543.32
A104: 440 | B104: Estructuras de hormigón armado | C104: Base, Columna y Plataforma de H°A° para Tanque de Agua Elevado | D104: estructura para T.A. hasta 1.100lts. (altura 4,00mts.) | E104: Unidad | F104: 511495.53 | H104: =CONCATENATE(B104," ",C104) -> Estructuras de hormigón armado Base, Columna y Plataforma de H°A° para Tanque de Agua Elevado | I104: =F104 -> 511495.53
A105: 434 | B105: Estructuras de hormigón armado | C105: Columna H°A° 15x20 (Hierro 10mm) | D105: con hierro del 10mm y estribos del 6 c/20cm. | E105: Metro lineal | F105: 23030.95 | H105: =CONCATENATE(B105," ",C105) -> Estructuras de hormigón armado Columna H°A° 15x20 (Hierro 10mm) | I105: =F105 -> 23030.95
A106: 262 | B106: Estructuras de hormigón armado | C106: Columna H°A° 15x20 (Hierro 8mm) | D106: con hierro del 8 y estribos del 6 c/20cm. | E106: Metro lineal | F106: 23031.41 | H106: =CONCATENATE(B106," ",C106) -> Estructuras de hormigón armado Columna H°A° 15x20 (Hierro 8mm) | I106: =F106 -> 23031.41
A107: 435 | B107: Estructuras de hormigón armado | C107: Columna H°A° 15x25 (Hierro 10mm) | D107: con hierros del 10mm y estribos del 6 c/20cm. | E107: Metro lineal | F107: 23756.13 | H107: =CONCATENATE(B107," ",C107) -> Estructuras de hormigón armado Columna H°A° 15x25 (Hierro 10mm) | I107: =F107 -> 23756.13
A108: 261 | B108: Estructuras de hormigón armado | C108: Columna H°A° 20x20 (Hierro 8mm) | D108: con hierro del 8 y estribos del 6 c/20cm. | E108: Metro lineal | F108: 24310.97 | H108: =CONCATENATE(B108," ",C108) -> Estructuras de hormigón armado Columna H°A° 20x20 (Hierro 8mm) | I108: =F108 -> 24310.97
...

Sheet LISTADO DE ITEMS
A2: NOMBRE | B2: CATEGORIA | C2: DESCRIPCION | D2: UNIDAD | E2: PRECIO MO | F2: PRECIO MAT | G2: AJUSTE % | H2: ACTIVO | I2: PRECIO TOTAL
A3: Retiro de revestimientos en pared | B3: =VLOOKUP(A3,'Rendimientos V03'!$A$3:$F$1348,6,FALSE) -> Demolicion | D3: =VLOOKUP(A3,'Rendimientos V03'!$A$3:$F$1348,2,FALSE) -> m2 | E3: =IFERROR(VLOOKUP(A3,RELACIONES!$G$2:$I$55,3,FALSE),0) -> 31742.08 | F3: =IFERROR(SUMIF('Rendimientos V03'!$A$3:$A$348,A3,'Rendimientos V03'!$K$3:$K$348),0) -> 0 | I3: =E3+F3 -> 31742.08
A4: Retiro de pisos | B4: =VLOOKUP(A4,'Rendimientos V03'!$A$3:$F$1348,6,FALSE) -> Demolicion | D4: =VLOOKUP(A4,'Rendimientos V03'!$A$3:$F$1348,2,FALSE) -> m2 | E4: =IFERROR(VLOOKUP(A4,RELACIONES!$G$2:$I$55,3,FALSE),0) -> 33218.38 | F4: =IFERROR(SUMIF('Rendimientos V03'!$A$3:$A$348,A4,'Rendimientos V03'!$K$3:$K$348),0) -> 0 | I4: =E4+F4 -> 33218.38
A5: Picado de revoque | B5: =VLOOKUP(A5,'Rendimientos V03'!$A$3:$F$1348,6,FALSE) -> Demolicion | D5: =VLOOKUP(A5,'Rendimientos V03'!$A$3:$F$1348,2,FALSE) -> m2 | E5: =IFERROR(VLOOKUP(A5,RELACIONES!$G$2:$I$55,3,FALSE),0) -> 41830.57 | F5: =IFERROR(SUMIF('Rendimientos V03'!$A$3:$A$348,A5,'Rendimientos V03'!$K$3:$K$348),0) -> 0 | I5: =E5+F5 -> 41830.57
A6: Demolicion de pared | B6: =VLOOKUP(A6,'Rendimientos V03'!$A$3:$F$1348,6,FALSE) -> Demolicion | D6: =VLOOKUP(A6,'Rendimientos V03'!$A$3:$F$1348,2,FALSE) -> m2 | E6: =IFERROR(VLOOKUP(A6,RELACIONES!$G$2:$I$55,3,FALSE),0) -> 40231.176 | F6: =IFERROR(SUMIF('Rendimientos V03'!$A$3:$A$348,A6,'Rendimientos V03'!$K$3:$K$348),0) -> 0 | I6: =E6+F6 -> 40231.176
A7: Tabique de ladrillos hueco de 8x18x33 | B7: =VLOOKUP(A7,'Rendimientos V03'!$A$3:$F$1348,6,FALSE) -> Albañilería | D7: =VLOOKUP(A7,'Rendimientos V03'!$A$3:$F$1348,2,FALSE) -> m2 | E7: =IFERROR(VLOOKUP(A7,RELACIONES!$G$2:$I$55,3,FALSE),0) -> 14953.21 | F7: =IFERROR(SUMIF('Rendimientos V03'!$A$3:$A$348,A7,'Rendimientos V03'!$K$3:$K$348),0) -> 42377.134 | I7: =E7+F7 -> 57330.344
A8: Tabique de ladrillos hueco de 12x18x33 | B8: =VLOOKUP(A8,'Rendimientos V03'!$A$3:$F$1348,6,FALSE) -> Albañilería | D8: =VLOOKUP(A8,'Rendimientos V03'!$A$3:$F$1348,2,FALSE) -> m2 | E8: =IFERROR(VLOOKUP(A8,RELACIONES!$G$2:$I$55,3,FALSE),0) -> 18247.95 | F8: =IFERROR(SUMIF('Rendimientos V03'!$A$3:$A$348,A8,'Rendimientos V03'!$K$3:$K$348),0) -> 46881.917 | I8: =E8+F8 -> 65129.867
A9: Banquina (e=10 cm) | B9: =VLOOKUP(A9,'Rendimientos V03'!$A$3:$F$1348,6,FALSE) -> Albañilería | D9: =VLOOKUP(A9,'Rendimientos V03'!$A$3:$F$1348,2,FALSE) -> m2 | E9: =IFERROR(VLOOKUP(A9,RELACIONES!$G$2:$I$55,3,FALSE),0) -> 18085.58 | F9: =IFERROR(SUMIF('Rendimientos V03'!$A$3:$A$348,A9,'Rendimientos V03'!$K$3:$K$348),0) -> 8102.5391 | I9: =E9+F9 -> 26188.119
A10: Contrapiso de cascote sobre losa (e=10 cm) | B10: =VLOOKUP(A10,'Rendimientos V03'!$A$3:$F$1348,6,FALSE) -> Albañilería | D10: =VLOOKUP(A10,'Rendimientos V03'!$A$3:$F$1348,2,FALSE) -> m2 | E10: =IFERROR(VLOOKUP(A10,RELACIONES!$G$2:$I$55,3,FALSE),0) -> 18085.58 | F10: =IFERROR(SUMIF('Rendimientos V03'!$A$3:$A$348,A10,'Rendimientos V03'!$K$3:$K$348),0) -> 8102.5391 | I10: =E10+F10 -> 26188.119
A11: Membrana asfáltica sin aluminio | B11: =VLOOKUP(A11,'Rendimientos V03'!$A$3:$F$1348,6,FALSE) -> Albañilería | D11: =VLOOKUP(A11,'Rendimientos V03'!$A$3:$F$1348,2,FALSE) -> m2 | E11: =IFERROR(VLOOKUP(A11,RELACIONES!$G$2:$I$55,3,FALSE),0) -> 17129.59 | F11: =IFERROR(SUMIF('Rendimientos V03'!$A$3:$A$348,A11,'Rendimientos V03'!$K$3:$K$348),0) -> 12751.222 | I11: =E11+F11 -> 29880.812
A12: Membrana asfáltica con aluminio | B12: =VLOOKUP(A12,'Rendimientos V03'!$A$3:$F$1348,6,FALSE) -> Albañilería | D12: =VLOOKUP(A12,'Rendimientos V03'!$A$3:$F$1348,2,FALSE) -> m2 | E12: =IFERROR(VLOOKUP(A12,RELACIONES!$G$2:$I$55,3,FALSE),0) -> 17129.59 | F12: =IFERROR(SUMIF('Rendimientos V03'!$A$3:$A$348,A12,'Rendimientos V03'!$K$3:$K$348),0) -> 12751.222 | I12: =E12+F12 -> 29880.812
A13: Membrana asfáltica geotextil | B13: =VLOOKUP(A13,'Rendimientos V03'!$A$3:$F$1348,6,FALSE) -> Albañilería | D13: =VLOOKUP(A13,'Rendimientos V03'!$A$3:$F$1348,2,FALSE) -> m2 | E13: =IFERROR(VLOOKUP(A13,RELACIONES!$G$2:$I$55,3,FALSE),0) -> 17129.59 | F13: =IFERROR(SUMIF('Rendimientos V03'!$A$3:$A$348,A13,'Rendimientos V03'!$K$3:$K$348),0) -> 8800 | I13: =E13+F13 -> 25929.59
A14: Pintura asfáltica base acuosa | B14: =VLOOKUP(A14,'Rendimientos V03'!$A$3:$F$1348,6,FALSE) -> Albañilería | D14: =VLOOKUP(A14,'Rendimientos V03'!$A$3:$F$1348,2,FALSE) -> m2 | E14: =IFERROR(VLOOKUP(A14,RELACIONES!$G$2:$I$55,3,FALSE),0) -> 0 | F14: =IFERROR(SUMIF('Rendimientos V03'!$A$3:$A$348,A14,'Rendimientos V03'!$K$3:$K$348),0) -> 4741.6608 | I14: =E14+F14 -> 4741.6608
... A50: Revestimiento texturado exterior grueso (1 mano) | B50: =VLOOKUP(A50,'Rendimientos V03'!$A$3:$F$1348,6,FALSE) -> Pintura | D50: =VLOOKUP(A50,'Rendimientos V03'!$A$3:$F$1348,2,FALSE) -> m2 | E50: =IFERROR(VLOOKUP(A50,RELACIONES!$G$2:$I$55,3,FALSE),0) -> 21124.42 | F50: =IFERROR(SUMIF('Rendimientos V03'!$A$3:$A$348,A50,'Rendimientos V03'!$K$3:$K$348),0) -> 6683.8857 | I50: =E50+F50 -> 27808.306

Sheet Rendimientos V03
A2: TAREA | B2: UNIDAD | C2: MATERIAL | D2: STD MAT | E2: CANTIDAD | F2: RUBRO | G2: SUBRUBRO | H2: CONSUMIBLE | I2: EQUVALENTE MDO | J2: EQUVALENTE MAT | K2: $MAT
A3: Retiro de revestimientos en pared | B3: m2 | C3: MANO DE OBRA POR RETIRO DE CERAMICOS | D3: U | F3: Demolicion | I3: =IF(ISBLANK(A3),"",VLOOKUP(A3,RELACIONES!$G$3:$H$65,2,FALSE())) -> Demoliciones Picado de revestimiento | J3: =IF(ISBLANK(A3),"",VLOOKUP(C3,RELACIONES!$A$3:$B$70,2,FALSE)) -> #N/A | K3: =IF(ISBLANK(A3),"",VLOOKUP(J3,RELACIONES!$B$3:$E$83,4,FALSE)*E3) -> #N/A
I4: =IF(ISBLANK(A4),"",VLOOKUP(A4,RELACIONES!$G$3:$H$65,2,FALSE())) | J4: =IF(ISBLANK(A4),"",VLOOKUP(C4,RELACIONES!$A$3:$B$70,2,FALSE)) | K4: =IF(ISBLANK(A4),"",VLOOKUP(J4,RELACIONES!$B$3:$E$83,4,FALSE)*E4)
A5: Retiro de pisos | B5: m2 | C5: MANO DE OBRA POR RETIRO DE CERAMICOS | D5: U | F5: Demolicion | I5: =IF(ISBLANK(A5),"",VLOOKUP(A5,RELACIONES!$G$3:$H$65,2,FALSE())) -> Demoliciones De pisos | J5: =IF(ISBLANK(A5),"",VLOOKUP(C5,RELACIONES!$A$3:$B$70,2,FALSE)) -> #N/A | K5: =IF(ISBLANK(A5),"",VLOOKUP(J5,RELACIONES!$B$3:$E$83,4,FALSE)*E5) -> #N/A
I6: =IF(ISBLANK(A6),"",VLOOKUP(A6,RELACIONES!$G$3:$H$65,2,FALSE())) | J6: =IF(ISBLANK(A6),"",VLOOKUP(C6,RELACIONES!$A$3:$B$70,2,FALSE)) | K6: =IF(ISBLANK(A6),"",VLOOKUP(J6,RELACIONES!$B$3:$E$83,4,FALSE)*E6)
A7: Picado de revoque | B7: m2 | C7: Mano de obra por picado de revoque | D7: U | F7: Demolicion | I7: =IF(ISBLANK(A7),"",VLOOKUP(A7,RELACIONES!$G$3:$H$65,2,FALSE())) -> Demoliciones Picado de revoques | J7: =IF(ISBLANK(A7),"",VLOOKUP(C7,RELACIONES!$A$3:$B$70,2,FALSE)) -> #N/A | K7: =IF(ISBLANK(A7),"",VLOOKUP(J7,RELACIONES!$B$3:$E$83,4,FALSE)*E7) -> #N/A
I8: =IF(ISBLANK(A8),"",VLOOKUP(A8,RELACIONES!$G$3:$H$65,2,FALSE())) | J8: =IF(ISBLANK(A8),"",VLOOKUP(C8,RELACIONES!$A$3:$B$70,2,FALSE)) | K8: =IF(ISBLANK(A8),"",VLOOKUP(J8,RELACIONES!$B$3:$E$83,4,FALSE)*E8)
A9: Demolicion de pared | B9: m2 | C9: Mano de obra por demolicion | D9: U | E9: 1 | F9: Demolicion | I9: =IF(ISBLANK(A9),"",VLOOKUP(A9,RELACIONES!$G$3:$H$65,2,FALSE())) -> Demoliciones De mamposterías | J9: =IF(ISBLANK(A9),"",VLOOKUP(C9,RELACIONES!$A$3:$B$70,2,FALSE)) -> #N/A | K9: =IF(ISBLANK(A9),"",VLOOKUP(J9,RELACIONES!$B$3:$E$83,4,FALSE)*E9) -> #N/A
I10: =IF(ISBLANK(A10),"",VLOOKUP(A10,RELACIONES!$G$3:$H$65,2,FALSE())) | J10: =IF(ISBLANK(A10),"",VLOOKUP(C10,RELACIONES!$A$3:$B$70,2,FALSE)) | K10: =IF(ISBLANK(A10),"",VLOOKUP(J10,RELACIONES!$B$3:$E$83,4,FALSE)*E10)
A11: Tabique de ladrillos hueco de 8x18x33 | B11: m2 | C11: LADRILLOS HUECOS DE 8 CM (U) | D11: U | E11: 15.2 | F11: Albañilería | G11: Muros | H11: NO | I11: =IF(ISBLANK(A11),"",VLOOKUP(A11,RELACIONES!$G$3:$H$65,2,FALSE())) -> Mampostería de elevación con cemento tradicional Ladrillos huecos 08x18x33 | J11: =IF(ISBLANK(A11),"",VLOOKUP(C11,RELACIONES!$A$3:$B$70,2,FALSE)) -> Ladrillo Hueco 8x18x33 Loimar | K11: =IF(ISBLANK(A11),"",VLOOKUP(J11,RELACIONES!$B$3:$E$83,4,FALSE)*E11) -> 11916.648
A12: Tabique de ladrillos hueco de 8x18x33 | B12: m2 | C12: CEMENTO ALBAÑILERÍA (KG) | D12: KG | E12: 0.99 | F12: Albañilería | G12: Muros | H12: NO | I12: =IF(ISBLANK(A12),"",VLOOKUP(A12,RELACIONES!$G$3:$H$65,2,FALSE())) -> Mampostería de elevación con cemento tradicional Ladrillos huecos 08x18x33 | J12: =IF(ISBLANK(A12),"",VLOOKUP(C12,RELACIONES!$A$3:$B$70,2,FALSE)) -> Cemento Loma Negra | K12: =IF(ISBLANK(A12),"",VLOOKUP(J12,RELACIONES!$B$3:$E$83,4,FALSE)*E12) -> 309.7413
A13: Tabique de ladrillos hueco de 8x18x33 | B13: m2 | C13: ARENA (M3) | D13: M3 | E13: 0.009 | F13: Albañilería | G13: Muros | H13: NO | I13: =IF(ISBLANK(A13),"",VLOOKUP(A13,RELACIONES!$G$3:$H$65,2,FALSE())) -> Mampostería de elevación con cemento tradicional Ladrillos huecos 08x18x33 | J13: =IF(ISBLANK(A13),"",VLOOKUP(C13,RELACIONES!$A$3:$B$70,2,FALSE)) -> Arena fina | K13: =IF(ISBLANK(A13),"",VLOOKUP(J13,RELACIONES!$B$3:$E$83,4,FALSE)*E13) -> 490.06494
A14: Tabique de ladrillos hueco de 8x18x33 | B14: m2 | C14: CAL HIDRATADA (KG) | D14: KG | E14: 1.89 | F14: Albañilería | G14: Muros | H14: NO | I14: =IF(ISBLANK(A14),"",VLOOKUP(A14,RELACIONES!$G$3:$H$65,2,FALSE())) -> Mampostería de elevación con cemento tradicional Ladrillos huecos 08x18x33 | J14: =IF(ISBLANK(A14),"",VLOOKUP(C14,RELACIONES!$A$3:$B$70,2,FALSE)) -> Cal Hidráulica, Hidralit Avellaneda | K14: =IF(ISBLANK(A14),"",VLOOKUP(J14,RELACIONES!$B$3:$E$83,4,FALSE)*E14) -> 785.7297
A15: Tabique de ladrillos hueco de 8x18x33 | B15: m2 | C15: HIERRO ADN Ø6MM (ML) | D15: ML | E15: 3 | F15: Albañilería | G15: Muros | H15: SI | I15: =IF(ISBLANK(A15),"",VLOOKUP(A15,RELACIONES!$G$3:$H$65,2,FALSE())) -> Mampostería de elevación con cemento tradicional Ladrillos huecos 08x18x33 | J15: =IF(ISBLANK(A15),"",VLOOKUP(C15,RELACIONES!$A$3:$B$70,2,FALSE)) -> Hierro Torsionado del 6 mm | K15: =IF(ISBLANK(A15),"",VLOOKUP(J15,RELACIONES!$B$3:$E$83,4,FALSE)*E15) -> 28606.95
A16: Tabique de ladrillos hueco de 8x18x33 | B16: m2 | C16: DISCO DE CORTE PARA MAMPOSTERÍA (U) | D16: U | E16: 0.067 | F16: Albañilería | G16: Muros | H16: SI | I16: =IF(ISBLANK(A16),"",VLOOKUP(A16,RELACIONES!$G$3:$H$65,2,FALSE())) -> Mampostería de elevación con cemento tradicional Ladrillos huecos 08x18x33 | J16: =IF(ISBLANK(A16),"",VLOOKUP(C16,RELACIONES!$A$3:$B$70,2,FALSE)) -> DISCO DE CORTE PARA MAMPOSTERÍA (U) | K16: =IF(ISBLANK(A16),"",VLOOKUP(J16,RELACIONES!$B$3:$E$83,4,FALSE)*E16) -> 268
I17: =IF(ISBLANK(A17),"",VLOOKUP(A17,RELACIONES!$G$3:$H$65,2,FALSE())) | J17: =IF(ISBLANK(A17),"",VLOOKUP(C17,RELACIONES!$A$3:$B$70,2,FALSE)) | K17: =IF(ISBLANK(A17),"",VLOOKUP(J17,RELACIONES!$B$3:$E$83,4,FALSE)*E17)
A18: Tabique de ladrillos hueco de 12x18x33 | B18: m2 | C18: LADRILLOS HUECOS DE 12 CM (U) | D18: U | E18: 15.2 | F18: Albañilería | G18: Muros | H18: NO | I18: =IF(ISBLANK(A18),"",VLOOKUP(A18,RELACIONES!$G$3:$H$65,2,FALSE())) -> Mampostería de elevación con cemento tradicional Ladrillos huecos 12x18x33 | J18: =IF(ISBLANK(A18),"",VLOOKUP(C18,RELACIONES!$A$3:$B$70,2,FALSE)) -> Ladrillo Hueco 12x18x33 Loimar | K18: =IF(ISBLANK(A18),"",VLOOKUP(J18,RELACIONES!$B$3:$E$83,4,FALSE)*E18) -> 15605.08
A19: Tabique de ladrillos hueco de 12x18x33 | B19: m2 | C19: CEMENTO ALBAÑILERÍA (KG) | D19: KG | E19: 1.48 | F19: Albañilería | G19: Muros | H19: NO | I19: =IF(ISBLANK(A19),"",VLOOKUP(A19,RELACIONES!$G$3:$H$65,2,FALSE())) -> Mampostería de elevación con cemento tradicional Ladrillos huecos 12x18x33 | J19: =IF(ISBLANK(A19),"",VLOOKUP(C19,RELACIONES!$A$3:$B$70,2,FALSE)) -> Cemento Loma Negra | K19: =IF(ISBLANK(A19),"",VLOOKUP(J19,RELACIONES!$B$3:$E$83,4,FALSE)*E19) -> 463.0476
A20: Tabique de ladrillos hueco de 12x18x33 | B20: m2 | C20: ARENA (M3) | D20: M3 | E20: 0.014 | F20: Albañilería | G20: Muros | H20: NO | I20: =IF(ISBLANK(A20),"",VLOOKUP(A20,RELACIONES!$G$3:$H$65,2,FALSE())) -> Mampostería de elevación con cemento tradicional Ladrillos huecos 12x18x33 | J20: =IF(ISBLANK(A20),"",VLOOKUP(C20,RELACIONES!$A$3:$B$70,2,FALSE)) -> Arena fina | K20: =IF(ISBLANK(A20),"",VLOOKUP(J20,RELACIONES!$B$3:$E$83,4,FALSE)*E20) -> 762.32324
A21: Tabique de ladrillos hueco de 12x18x33 | B21: m2 | C21: CAL HIDRATADA (KG) | D21: KG | E21: 2.83 | F21: Albañilería | G21: Muros | H21: NO | I21: =IF(ISBLANK(A21),"",VLOOKUP(A21,RELACIONES!$G$3:$H$65,2,FALSE())) -> Mampostería de elevación con cemento tradicional Ladrillos huecos 12x18x33 | J21: =IF(ISBLANK(A21),"",VLOOKUP(C21,RELACIONES!$A$3:$B$70,2,FALSE)) -> Cal Hidráulica, Hidralit Avellaneda | K21: =IF(ISBLANK(A21),"",VLOOKUP(J21,RELACIONES!$B$3:$E$83,4,FALSE)*E21) -> 1176.5159
A22: Tabique de ladrillos hueco de 12x18x33 | B22: m2 | C22: HIERRO ADN Ø6MM (ML) | D22: ML | E22: 3 | F22: Albañilería | G22: Muros | H22: SI | I22: =IF(ISBLANK(A22),"",VLOOKUP(A22,RELACIONES!$G$3:$H$65,2,FALSE())) -> Mampostería de elevación con cemento tradicional Ladrillos huecos 12x18x33 | J22: =IF(ISBLANK(A22),"",VLOOKUP(C22,RELACIONES!$A$3:$B$70,2,FALSE)) -> Hierro Torsionado del 6 mm | K22: =IF(ISBLANK(A22),"",VLOOKUP(J22,RELACIONES!$B$3:$E$83,4,FALSE)*E22) -> 28606.95
A23: Tabique de ladrillos hueco de 12x18x33 | B23: m2 | C23: DISCO DE CORTE PARA MAMPOSTERÍA (U) | D23: U | E23: 0.067 | F23: Albañilería | G23: Muros | H23: SI | I23: =IF(ISBLANK(A23),"",VLOOKUP(A23,RELACIONES!$G$3:$H$65,2,FALSE())) -> Mampostería de elevación con cemento tradicional Ladrillos huecos 12x18x33 | J23: =IF(ISBLANK(A23),"",VLOOKUP(C23,RELACIONES!$A$3:$B$70,2,FALSE)) -> DISCO DE CORTE PARA MAMPOSTERÍA (U) | K23: =IF(ISBLANK(A23),"",VLOOKUP(J23,RELACIONES!$B$3:$E$83,4,FALSE)*E23) -> 268
I24: =IF(ISBLANK(A24),"",VLOOKUP(A24,RELACIONES!$G$3:$H$65,2,FALSE())) | J24: =IF(ISBLANK(A24),"",VLOOKUP(C24,RELACIONES!$A$3:$B$70,2,FALSE)) | K24: =IF(ISBLANK(A24),"",VLOOKUP(J24,RELACIONES!$B$3:$E$83,4,FALSE)*E24)
I25: =IF(ISBLANK(A25),"",VLOOKUP(A25,RELACIONES!$G$3:$H$65,2,FALSE())) | J25: =IF(ISBLANK(A25),"",VLOOKUP(C25,RELACIONES!$A$3:$B$70,2,FALSE)) | K25: =IF(ISBLANK(A25),"",VLOOKUP(J25,RELACIONES!$B$3:$E$83,4,FALSE)*E25)
A26: Banquina (e=10 cm) | B26: m2 | C26: CEMENTO ALBAÑILERÍA (KG) | D26: KG | E26: 1.8 | F26: Albañilería | G26: Contrapisos | H26: NO | I26: =IF(ISBLANK(A26),"",VLOOKUP(A26,RELACIONES!$G$3:$H$65,2,FALSE())) -> Contrapisos De cascotes s/ terreno natural. Esp: 10cm. (con cemento de albañilería) | J26: =IF(ISBLANK(A26),"",VLOOKUP(C26,RELACIONES!$A$3:$B$70,2,FALSE)) -> Cemento Loma Negra | K26: =IF(ISBLANK(A26),"",VLOOKUP(J26,RELACIONES!$B$3:$E$83,4,FALSE)*E26) -> 563.166
A27: Banquina (e=10 cm) | B27: m2 | C27: ARENA (M3) | D27: M3 | E27: 0.0425 | F27: Albañilería | G27: Contrapisos | H27: NO | I27: =IF(ISBLANK(A27),"",VLOOKUP(A27,RELACIONES!$G$3:$H$65,2,FALSE())) -> Contrapisos De cascotes s/ terreno natural. Esp: 10cm. (con cemento de albañilería) | J27: =IF(ISBLANK(A27),"",VLOOKUP(C27,RELACIONES!$A$3:$B$70,2,FALSE)) -> Arena fina | K27: =IF(ISBLANK(A27),"",VLOOKUP(J27,RELACIONES!$B$3:$E$83,4,FALSE)*E27) -> 2314.1955
A28: Banquina (e=10 cm) | B28: m2 | C28: CAL HIDRATADA (KG) | D28: KG | E28: 6.75 | F28: Albañilería | G28: Contrapisos | H28: NO | I28: =IF(ISBLANK(A28),"",VLOOKUP(A28,RELACIONES!$G$3:$H$65,2,FALSE())) -> Contrapisos De cascotes s/ terreno natural. Esp: 10cm. (con cemento de albañilería) | J28: =IF(ISBLANK(A28),"",VLOOKUP(C28,RELACIONES!$A$3:$B$70,2,FALSE)) -> Cal Hidráulica, Hidralit Avellaneda | K28: =IF(ISBLANK(A28),"",VLOOKUP(J28,RELACIONES!$B$3:$E$83,4,FALSE)*E28) -> 2806.1775
A29: Banquina (e=10 cm) | B29: m2 | C29: CASCOTE DE LADRILLOS (M3) | D29: M3 | E29: 0.085 | F29: Albañilería | G29: Contrapisos | H29: NO | I29: =IF(ISBLANK(A29),"",VLOOKUP(A29,RELACIONES!$G$3:$H$65,2,FALSE())) -> Contrapisos De cascotes s/ terreno natural. Esp: 10cm. (con cemento de albañilería) | J29: =IF(ISBLANK(A29),"",VLOOKUP(C29,RELACIONES!$A$3:$B$70,2,FALSE)) -> CASCOTE DE LADRILLOS (M3) | K29: =IF(ISBLANK(A29),"",VLOOKUP(J29,RELACIONES!$B$3:$E$83,4,FALSE)*E29) -> 2295
A30: Banquina (e=10 cm) | B30: m2 | C30: FRATACHO (U) | D30: U | E30: 0.007 | F30: Albañilería | G30: Contrapisos | H30: SI | I30: =IF(ISBLANK(A30),"",VLOOKUP(A30,RELACIONES!$G$3:$H$65,2,FALSE())) -> Contrapisos De cascotes s/ terreno natural. Esp: 10cm. (con cemento de albañilería) | J30: =IF(ISBLANK(A30),"",VLOOKUP(C30,RELACIONES!$A$3:$B$70,2,FALSE)) -> FRATACHO (U) | K30: =IF(ISBLANK(A30),"",VLOOKUP(J30,RELACIONES!$B$3:$E$83,4,FALSE)*E30) -> 24.5
A31: Banquina (e=10 cm) | B31: m2 | C31: LLANA LISA (U) | D31: U | E31: 0.007 | F31: Albañilería | G31: Contrapisos | H31: SI | I31: =IF(ISBLANK(A31),"",VLOOKUP(A31,RELACIONES!$G$3:$H$65,2,FALSE())) -> Contrapisos De cascotes s/ terreno natural. Esp: 10cm. (con cemento de albañilería) | J31: =IF(ISBLANK(A31),"",VLOOKUP(C31,RELACIONES!$A$3:$B$70,2,FALSE)) -> LLANA LISA (U) | K31: =IF(ISBLANK(A31),"",VLOOKUP(J31,RELACIONES!$B$3:$E$83,4,FALSE)*E31) -> 73.5
A32: Banquina (e=10 cm) | B32: m2 | C32: CARTÓN CORRUGADO (M2) | D32: M2 | E32: 0.05 | F32: Albañilería | G32: Contrapisos | H32: SI | I32: =IF(ISBLANK(A32),"",VLOOKUP(A32,RELACIONES!$G$3:$H$65,2,FALSE())) -> Contrapisos De cascotes s/ terreno natural. Esp: 10cm. (con cemento de albañilería) | J32: =IF(ISBLANK(A32),"",VLOOKUP(C32,RELACIONES!$A$3:$B$70,2,FALSE)) -> CARTÓN CORRUGADO (M2) | K32: =IF(ISBLANK(A32),"",VLOOKUP(J32,RELACIONES!$B$3:$E$83,4,FALSE)*E32) -> 26
I33: =IF(ISBLANK(A33),"",VLOOKUP(A33,RELACIONES!$G$3:$H$65,2,FALSE())) | J33: =IF(ISBLANK(A33),"",VLOOKUP(C33,RELACIONES!$A$3:$B$70,2,FALSE)) | K33: =IF(ISBLANK(A33),"",VLOOKUP(J33,RELACIONES!$B$3:$E$83,4,FALSE)*E33)
A34: Contrapiso de cascote sobre losa (e=10 cm) | B34: m2 | C34: CEMENTO ALBAÑILERÍA (KG) | D34: KG | E34: 1.8 | F34: Albañilería | G34: Contrapisos | H34: NO | I34: =IF(ISBLANK(A34),"",VLOOKUP(A34,RELACIONES!$G$3:$H$65,2,FALSE())) -> Contrapisos De cascotes s/ terreno natural. Esp: 10cm. (con cemento de albañilería) | J34: =IF(ISBLANK(A34),"",VLOOKUP(C34,RELACIONES!$A$3:$B$70,2,FALSE)) -> Cemento Loma Negra | K34: =IF(ISBLANK(A34),"",VLOOKUP(J34,RELACIONES!$B$3:$E$83,4,FALSE)*E34) -> 563.166
A35: Contrapiso de cascote sobre losa (e=10 cm) | B35: m2 | C35: ARENA (M3) | D35: M3 | E35: 0.0425 | F35: Albañilería | G35: Contrapisos | H35: NO | I35: =IF(ISBLANK(A35),"",VLOOKUP(A35,RELACIONES!$G$3:$H$65,2,FALSE())) -> Contrapisos De cascotes s/ terreno natural. Esp: 10cm. (con cemento de albañilería) | J35: =IF(ISBLANK(A35),"",VLOOKUP(C35,RELACIONES!$A$3:$B$70,2,FALSE)) -> Arena fina | K35: =IF(ISBLANK(A35),"",VLOOKUP(J35,RELACIONES!$B$3:$E$83,4,FALSE)*E35) -> 2314.1955
A36: Contrapiso de cascote sobre losa (e=10 cm) | B36: m2 | C36: CAL HIDRATADA (KG) | D36: KG | E36: 6.75 | F36: Albañilería | G36: Contrapisos | H36: NO | I36: =IF(ISBLANK(A36),"",VLOOKUP(A36,RELACIONES!$G$3:$H$65,2,FALSE())) -> Contrapisos De cascotes s/ terreno natural. Esp: 10cm. (con cemento de albañilería) | J36: =IF(ISBLANK(A36),"",VLOOKUP(C36,RELACIONES!$A$3:$B$70,2,FALSE)) -> Cal Hidráulica, Hidralit Avellaneda | K36: =IF(ISBLANK(A36),"",VLOOKUP(J36,RELACIONES!$B$3:$E$83,4,FALSE)*E36) -> 2806.1775
A37: Contrapiso de cascote sobre losa (e=10 cm) | B37: m2 | C37: CASCOTE DE LADRILLOS (M3) | D37: M3 | E37: 0.085 | F37: Albañilería | G37: Contrapisos | H37: NO | I37: =IF(ISBLANK(A37),"",VLOOKUP(A37,RELACIONES!$G$3:$H$65,2,FALSE())) -> Contrapisos De cascotes s/ terreno natural. Esp: 10cm. (con cemento de albañilería) | J37: =IF(ISBLANK(A37),"",VLOOKUP(C37,RELACIONES!$A$3:$B$70,2,FALSE)) -> CASCOTE DE LADRILLOS (M3) | K37: =IF(ISBLANK(A37),"",VLOOKUP(J37,RELACIONES!$B$3:$E$83,4,FALSE)*E37) -> 2295
A38: Contrapiso de cascote sobre losa (e=10 cm) | B38: m2 | C38: FRATACHO (U) | D38: U | E38: 0.007 | F38: Albañilería | G38: Contrapisos | H38: SI | I38: =IF(ISBLANK(A38),"",VLOOKUP(A38,RELACIONES!$G$3:$H$65,2,FALSE())) -> Contrapisos De cascotes s/ terreno natural. Esp: 10cm. (con cemento de albañilería) | J38: =IF(ISBLANK(A38),"",VLOOKUP(C38,RELACIONES!$A$3:$B$70,2,FALSE)) -> FRATACHO (U) | K38: =IF(ISBLANK(A38),"",VLOOKUP(J38,RELACIONES!$B$3:$E$83,4,FALSE)*E38) -> 24.5
A39: Contrapiso de cascote sobre losa (e=10 cm) | B39: m2 | C39: LLANA LISA (U) | D39: U | E39: 0.007 | F39: Albañilería | G39: Contrapisos | H39: SI | I39: =IF(ISBLANK(A39),"",VLOOKUP(A39,RELACIONES!$G$3:$H$65,2,FALSE())) -> Contrapisos De cascotes s/ terreno natural. Esp: 10cm. (con cemento de albañilería) | J39: =IF(ISBLANK(A39),"",VLOOKUP(C39,RELACIONES!$A$3:$B$70,2,FALSE)) -> LLANA LISA (U) | K39: =IF(ISBLANK(A39),"",VLOOKUP(J39,RELACIONES!$B$3:$E$83,4,FALSE)*E39) -> 73.5
A40: Contrapiso de cascote sobre losa (e=10 cm) | B40: m2 | C40: CARTÓN CORRUGADO (M2) | D40: M2 | E40: 0.05 | F40: Albañilería | G40: Contrapisos | H40: SI | I40: =IF(ISBLANK(A40),"",VLOOKUP(A40,RELACIONES!$G$3:$H$65,2,FALSE())) -> Contrapisos De cascotes s/ terreno natural. Esp: 10cm. (con cemento de albañilería) | J40: =IF(ISBLANK(A40),"",VLOOKUP(C40,RELACIONES!$A$3:$B$70,2,FALSE)) -> CARTÓN CORRUGADO (M2) | K40: =IF(ISBLANK(A40),"",VLOOKUP(J40,RELACIONES!$B$3:$E$83,4,FALSE)*E40) -> 26
I41: =IF(ISBLANK(A41),"",VLOOKUP(A41,RELACIONES!$G$3:$H$65,2,FALSE())) | J41: =IF(ISBLANK(A41),"",VLOOKUP(C41,RELACIONES!$A$3:$B$70,2,FALSE)) | K41: =IF(ISBLANK(A41),"",VLOOKUP(J41,RELACIONES!$B$3:$E$83,4,FALSE)*E41)
A42: Membrana asfáltica sin aluminio | B42: m2 | C42: MEMBRANA ASFÁLTICA SIN ALUMINIO (M2) | D42: M2 | E42: 1.1 | F42: Albañilería | G42: Contrapisos - Aislaciones | H42: NO | I42: =IF(ISBLANK(A42),"",VLOOKUP(A42,RELACIONES!$G$3:$H$65,2,FALSE())) -> Cubiertas Colocación de membrana asfáltica con imprimación de superficie | J42: =IF(ISBLANK(A42),"",VLOOKUP(C42,RELACIONES!$A$3:$B$70,2,FALSE)) -> Membrana Asfáltica c/aluminio Megaflex esp. 4mm | K42: =IF(ISBLANK(A42),"",VLOOKUP(J42,RELACIONES!$B$3:$E$83,4,FALSE)*E42) -> 12751.222
I43: =IF(ISBLANK(A43),"",VLOOKUP(A43,RELACIONES!$G$3:$H$65,2,FALSE())) | J43: =IF(ISBLANK(A43),"",VLOOKUP(C43,RELACIONES!$A$3:$B$70,2,FALSE)) | K43: =IF(ISBLANK(A43),"",VLOOKUP(J43,RELACIONES!$B$3:$E$83,4,FALSE)*E43)
A44: Membrana asfáltica con aluminio | B44: m2 | C44: MEMBRANA ASFÁLTICA CON ALUMINIO (M2) | D44: M2 | E44: 1.1 | F44: Albañilería | G44: Contrapisos - Aislaciones | H44: NO | I44: =IF(ISBLANK(A44),"",VLOOKUP(A44,RELACIONES!$G$3:$H$65,2,FALSE())) -> Cubiertas Colocación de membrana asfáltica con imprimación de superficie | J44: =IF(ISBLANK(A44),"",VLOOKUP(C44,RELACIONES!$A$3:$B$70,2,FALSE)) -> Membrana Asfáltica c/aluminio Megaflex esp. 4mm | K44: =IF(ISBLANK(A44),"",VLOOKUP(J44,RELACIONES!$B$3:$E$83,4,FALSE)*E44) -> 12751.222
I45: =IF(ISBLANK(A45),"",VLOOKUP(A45,RELACIONES!$G$3:$H$65,2,FALSE())) | J45: =IF(ISBLANK(A45),"",VLOOKUP(C45,RELACIONES!$A$3:$B$70,2,FALSE)) | K45: =IF(ISBLANK(A45),"",VLOOKUP(J45,RELACIONES!$B$3:$E$83,4,FALSE)*E45)
A46: Membrana asfáltica geotextil | B46: m2 | C46: MEMBRANA ASFÁLTICA GEOTEXTIL (M2) | D46: M2 | E46: 1.1 | F46: Albañilería | G46: Contrapisos - Aislaciones | H46: NO | I46: =IF(ISBLANK(A46),"",VLOOKUP(A46,RELACIONES!$G$3:$H$65,2,FALSE())) -> Cubiertas Colocación de membrana asfáltica con imprimación de superficie | J46: =IF(ISBLANK(A46),"",VLOOKUP(C46,RELACIONES!$A$3:$B$70,2,FALSE)) -> MEMBRANA ASFÁLTICA GEOTEXTIL (M2) | K46: =IF(ISBLANK(A46),"",VLOOKUP(J46,RELACIONES!$B$3:$E$83,4,FALSE)*E46) -> 8800
I47: =IF(ISBLANK(A47),"",VLOOKUP(A47,RELACIONES!$G$3:$H$65,2,FALSE())) | J47: =IF(ISBLANK(A47),"",VLOOKUP(C47,RELACIONES!$A$3:$B$70,2,FALSE)) | K47: =IF(ISBLANK(A47),"",VLOOKUP(J47,RELACIONES!$B$3:$E$83,4,FALSE)*E47)
A48: Pintura asfáltica base acuosa | B48: m2 | C48: PINTURA ASFÁLTICA ACUOSA (KG) | D48: KG | E48: 0.5 | F48: Albañilería | G48: Contrapisos - Aislaciones | H48: NO | I48: =IF(ISBLANK(A48),"",VLOOKUP(A48,RELACIONES!$G$3:$H$65,2,FALSE())) | J48: =IF(ISBLANK(A48),"",VLOOKUP(C48,RELACIONES!$A$3:$B$70,2,FALSE)) -> Pintura asfáltica Megaflex, base solvente, 18L | K48: =IF(ISBLANK(A48),"",VLOOKUP(J48,RELACIONES!$B$3:$E$83,4,FALSE)*E48) -> 4741.6608
I49: =IF(ISBLANK(A49),"",VLOOKUP(A49,RELACIONES!$G$3:$H$65,2,FALSE())) | J49: =IF(ISBLANK(A49),"",VLOOKUP(C49,RELACIONES!$A$3:$B$70,2,FALSE)) | K49: =IF(ISBLANK(A49),"",VLOOKUP(J49,RELACIONES!$B$3:$E$83,4,FALSE)*E49)
A50: Pintura asfáltica base solvente | B50: m2 | C50: PINTURA ASFÁLTICA SOLVENTE (KG) | D50: KG | E50: 0.5 | F50: Albañilería | G50: Contrapisos - Aislaciones | H50: NO | I50: =IF(ISBLANK(A50),"",VLOOKUP(A50,RELACIONES!$G$3:$H$65,2,FALSE())) | J50: =IF(ISBLANK(A50),"",VLOOKUP(C50,RELACIONES!$A$3:$B$70,2,FALSE)) -> Pintura asfáltica Megaflex, base solvente, 18L | K50: =IF(ISBLANK(A50),"",VLOOKUP(J50,RELACIONES!$B$3:$E$83,4,FALSE)*E50) -> 4741.6608
I51: =IF(ISBLANK(A51),"",VLOOKUP(A51,RELACIONES!$G$3:$H$65,2,FALSE())) | J51: =IF(ISBLANK(A51),"",VLOOKUP(C51,RELACIONES!$A$3:$B$70,2,FALSE)) | K51: =IF(ISBLANK(A51),"",VLOOKUP(J51,RELACIONES!$B$3:$E$83,4,FALSE)*E51)
A52: Film polietileno 200µ | B52: m2 | C52: FILM POLIETILENO 200µ (M2) | D52: M2 | E52: 1.1 | F52: Albañilería | G52: Contrapisos - Aislaciones | H52: NO | I52: =IF(ISBLANK(A52),"",VLOOKUP(A52,RELACIONES!$G$3:$H$65,2,FALSE())) | J52: =IF(ISBLANK(A52),"",VLOOKUP(C52,RELACIONES!$A$3:$B$70,2,FALSE)) -> FILM POLIETILENO 200µ (M2) | K52: =IF(ISBLANK(A52),"",VLOOKUP(J52,RELACIONES!$B$3:$E$83,4,FALSE)*E52) -> 880
I53: =IF(ISBLANK(A53),"",VLOOKUP(A53,RELACIONES!$G$3:$H$65,2,FALSE())) | J53: =IF(ISBLANK(A53),"",VLOOKUP(C53,RELACIONES!$A$3:$B$70,2,FALSE)) | K53: =IF(ISBLANK(A53),"",VLOOKUP(J53,RELACIONES!$B$3:$E$83,4,FALSE)*E53)
A54: Carpeta de cemento 1:3 (e=2 cm) | B54: m2 | C54: CEMENTO ALBAÑILERÍA (KG) | D54: KG | E54: 9.08 | F54: Albañilería | G54: Carpetas | H54: NO | I54: =IF(ISBLANK(A54),"",VLOOKUP(A54,RELACIONES!$G$3:$H$65,2,FALSE())) -> Carpetas Alisado de cemento para piso (Esp:2cm) | J54: =IF(ISBLANK(A54),"",VLOOKUP(C54,RELACIONES!$A$3:$B$70,2,FALSE)) -> Cemento Loma Negra | K54: =IF(ISBLANK(A54),"",VLOOKUP(J54,RELACIONES!$B$3:$E$83,4,FALSE)*E54) -> 2840.8596
A55: Carpeta de cemento 1:3 (e=2 cm) | B55: m2 | C55: ARENA (M3) | D55: M3 | E55: 0.0218 | F55: Albañilería | G55: Carpetas | H55: NO | I55: =IF(ISBLANK(A55),"",VLOOKUP(A55,RELACIONES!$G$3:$H$65,2,FALSE())) -> Carpetas Alisado de cemento para piso (Esp:2cm) | J55: =IF(ISBLANK(A55),"",VLOOKUP(C55,RELACIONES!$A$3:$B$70,2,FALSE)) -> Arena fina | K55: =IF(ISBLANK(A55),"",VLOOKUP(J55,RELACIONES!$B$3:$E$83,4,FALSE)*E55) -> 1187.0462
A56: Carpeta de cemento 1:3 (e=2 cm) | B56: m2 | C56: FRATACHO (U) | D56: U | E56: 0.007 | F56: Albañilería | G56: Carpetas | H56: SI | I56: =IF(ISBLANK(A56),"",VLOOKUP(A56,RELACIONES!$G$3:$H$65,2,FALSE())) -> Carpetas Alisado de cemento para piso (Esp:2cm) | J56: =IF(ISBLANK(A56),"",VLOOKUP(C56,RELACIONES!$A$3:$B$70,2,FALSE)) -> FRATACHO (U) | K56: =IF(ISBLANK(A56),"",VLOOKUP(J56,RELACIONES!$B$3:$E$83,4,FALSE)*E56) -> 24.5
A57: Carpeta de cemento 1:3 (e=2 cm) | B57: m2 | C57: FRATACHO ABRASIVO (U) | D57: U | E57: 0.013 | F57: Albañilería | G57: Carpetas | H57: SI | I57: =IF(ISBLANK(A57),"",VLOOKUP(A57,RELACIONES!$G$3:$H$65,2,FALSE())) -> Carpetas Alisado de cemento para piso (Esp:2cm) | J57: =IF(ISBLANK(A57),"",VLOOKUP(C57,RELACIONES!$A$3:$B$70,2,FALSE)) -> FRATACHO ABRASIVO (U) | K57: =IF(ISBLANK(A57),"",VLOOKUP(J57,RELACIONES!$B$3:$E$83,4,FALSE)*E57) -> 58.5
A58: Carpeta de cemento 1:3 (e=2 cm) | B58: m2 | C58: LLANA LISA (U) | D58: U | E58: 0.007 | F58: Albañilería | G58: Carpetas | H58: SI | I58: =IF(ISBLANK(A58),"",VLOOKUP(A58,RELACIONES!$G$3:$H$65,2,FALSE())) -> Carpetas Alisado de cemento para piso (Esp:2cm) | J58: =IF(ISBLANK(A58),"",VLOOKUP(C58,RELACIONES!$A$3:$B$70,2,FALSE)) -> LLANA LISA (U) | K58: =IF(ISBLANK(A58),"",VLOOKUP(J58,RELACIONES!$B$3:$E$83,4,FALSE)*E58) -> 73.5
I59: =IF(ISBLANK(A59),"",VLOOKUP(A59,RELACIONES!$G$3:$H$65,2,FALSE())) | J59: =IF(ISBLANK(A59),"",VLOOKUP(C59,RELACIONES!$A$3:$B$70,2,FALSE)) | K59: =IF(ISBLANK(A59),"",VLOOKUP(J59,RELACIONES!$B$3:$E$83,4,FALSE)*E59)
A60: Carpeta de cemento 1:3 c/hidrófugo (e=2 cm) | B60: m2 | C60: CEMENTO ALBAÑILERÍA (KG) | D60: KG | E60: 9.08 | F60: Albañilería | G60: Carpetas | H60: NO | I60: =IF(ISBLANK(A60),"",VLOOKUP(A60,RELACIONES!$G$3:$H$65,2,FALSE())) -> Carpetas Hidrofuga s/contrapiso (Esp: 2cm) | J60: =IF(ISBLANK(A60),"",VLOOKUP(C60,RELACIONES!$A$3:$B$70,2,FALSE)) -> Cemento Loma Negra | K60: =IF(ISBLANK(A60),"",VLOOKUP(J60,RELACIONES!$B$3:$E$83,4,FALSE)*E60) -> 2840.8596
A61: Carpeta de cemento 1:3 c/hidrófugo (e=2 cm) | B61: m2 | C61: ARENA (M3) | D61: M3 | E61: 0.024 | F61: Albañilería | G61: Carpetas | H61: NO | I61: =IF(ISBLANK(A61),"",VLOOKUP(A61,RELACIONES!$G$3:$H$65,2,FALSE())) -> Carpetas Hidrofuga s/contrapiso (Esp: 2cm) | J61: =IF(ISBLANK(A61),"",VLOOKUP(C61,RELACIONES!$A$3:$B$70,2,FALSE)) -> Arena fina | K61: =IF(ISBLANK(A61),"",VLOOKUP(J61,RELACIONES!$B$3:$E$83,4,FALSE)*E61) -> 1306.8398
A62: Carpeta de cemento 1:3 c/hidrófugo (e=2 cm) | B62: m2 | C62: HIDRÓFUGO EN PASTA (KG) | D62: KG | E62: 0.36 | F62: Albañilería | G62: Carpetas | H62: NO | I62: =IF(ISBLANK(A62),"",VLOOKUP(A62,RELACIONES!$G$3:$H$65,2,FALSE())) -> Carpetas Hidrofuga s/contrapiso (Esp: 2cm) | J62: =IF(ISBLANK(A62),"",VLOOKUP(C62,RELACIONES!$A$3:$B$70,2,FALSE)) -> Hidrófugo Sika, caja x 20kg | K62: =IF(ISBLANK(A62),"",VLOOKUP(J62,RELACIONES!$B$3:$E$83,4,FALSE)*E62) -> 880.66836
A63: Carpeta de cemento 1:3 c/hidrófugo (e=2 cm) | B63: m2 | C63: FRATACHO (U) | D63: U | E63: 0.007 | F63: Albañilería | G63: Carpetas | H63: SI | I63: =IF(ISBLANK(A63),"",VLOOKUP(A63,RELACIONES!$G$3:$H$65,2,FALSE())) -> Carpetas Hidrofuga s/contrapiso (Esp: 2cm) | J63: =IF(ISBLANK(A63),"",VLOOKUP(C63,RELACIONES!$A$3:$B$70,2,FALSE)) -> FRATACHO (U) | K63: =IF(ISBLANK(A63),"",VLOOKUP(J63,RELACIONES!$B$3:$E$83,4,FALSE)*E63) -> 24.5
A64: Carpeta de cemento 1:3 c/hidrófugo (e=2 cm) | B64: m2 | C64: FRATACHO ABRASIVO (U) | D64: U | E64: 0.013 | F64: Albañilería | G64: Carpetas | H64: SI | I64: =IF(ISBLANK(A64),"",VLOOKUP(A64,RELACIONES!$G$3:$H$65,2,FALSE())) -> Carpetas Hidrofuga s/contrapiso (Esp: 2cm) | J64: =IF(ISBLANK(A64),"",VLOOKUP(C64,RELACIONES!$A$3:$B$70,2,FALSE)) -> FRATACHO ABRASIVO (U) | K64: =IF(ISBLANK(A64),"",VLOOKUP(J64,RELACIONES!$B$3:$E$83,4,FALSE)*E64) -> 58.5
A65: Carpeta de cemento 1:3 c/hidrófugo (e=2 cm) | B65: m2 | C65: LLANA LISA (U) | D65: U | E65: 0.007 | F65: Albañilería | G65: Carpetas | H65: SI | I65: =IF(ISBLANK(A65),"",VLOOKUP(A65,RELACIONES!$G$3:$H$65,2,FALSE())) -> Carpetas Hidrofuga s/contrapiso (Esp: 2cm) | J65: =IF(ISBLANK(A65),"",VLOOKUP(C65,RELACIONES!$A$3:$B$70,2,FALSE)) -> LLANA LISA (U) | K65: =IF(ISBLANK(A65),"",VLOOKUP(J65,RELACIONES!$B$3:$E$83,4,FALSE)*E65) -> 73.5
I66: =IF(ISBLANK(A66),"",VLOOKUP(A66,RELACIONES!$G$3:$H$65,2,FALSE())) | J66: =IF(ISBLANK(A66),"",VLOOKUP(C66,RELACIONES!$A$3:$B$70,2,FALSE)) | K66: =IF(ISBLANK(A66),"",VLOOKUP(J66,RELACIONES!$B$3:$E$83,4,FALSE)*E66)
A67: Revoque grueso + revoque fino (e grueso=2 cm) | B67: m2 | C67: CEMENTO ALBAÑILERÍA (KG) | D67: KG | E67: 2.52 | F67: Albañilería | G67: Revoques | H67: NO | I67: =IF(ISBLANK(A67),"",VLOOKUP(A67,RELACIONES!$G$3:$H$65,2,FALSE())) -> Revoques 2 en 1: grueso y fino interior | J67: =IF(ISBLANK(A67),"",VLOOKUP(C67,RELACIONES!$A$3:$B$70,2,FALSE)) -> Cemento Loma Negra | K67: =IF(ISBLANK(A67),"",VLOOKUP(J67,RELACIONES!$B$3:$E$83,4,FALSE)*E67) -> 788.4324
A68: Revoque grueso + revoque fino (e grueso=2 cm) | B68: m2 | C68: ARENA (M3) | D68: M3 | E68: 0.028 | F68: Albañilería | G68: Revoques | H68: NO | I68: =IF(ISBLANK(A68),"",VLOOKUP(A68,RELACIONES!$G$3:$H$65,2,FALSE())) -> Revoques 2 en 1: grueso y fino interior | J68: =IF(ISBLANK(A68),"",VLOOKUP(C68,RELACIONES!$A$3:$B$70,2,FALSE)) -> Arena fina | K68: =IF(ISBLANK(A68),"",VLOOKUP(J68,RELACIONES!$B$3:$E$83,4,FALSE)*E68) -> 1524.6465
A69: Revoque grueso + revoque fino (e grueso=2 cm) | B69: m2 | C69: CAL HIDRATADA (KG) | D69: KG | E69: 4.52 | F69: Albañilería | G69: Revoques | H69: NO | I69: =IF(ISBLANK(A69),"",VLOOKUP(A69,RELACIONES!$G$3:$H$65,2,FALSE())) -> Revoques 2 en 1: grueso y fino interior | J69: =IF(ISBLANK(A69),"",VLOOKUP(C69,RELACIONES!$A$3:$B$70,2,FALSE)) -> Cal Hidráulica, Hidralit Avellaneda | K69: =IF(ISBLANK(A69),"",VLOOKUP(J69,RELACIONES!$B$3:$E$83,4,FALSE)*E69) -> 1879.0996
A70: Revoque grueso + revoque fino (e grueso=2 cm) | B70: m2 | C70: CAL AÉREA (KG) | D70: KG | E70: 2.2 | F70: Albañilería | G70: Revoques | H70: NO | I70: =IF(ISBLANK(A70),"",VLOOKUP(A70,RELACIONES!$G$3:$H$65,2,FALSE())) -> Revoques 2 en 1: grueso y fino interior | J70: =IF(ISBLANK(A70),"",VLOOKUP(C70,RELACIONES!$A$3:$B$70,2,FALSE)) -> Cal Aérea Hidratada El Milagro | K70: =IF(ISBLANK(A70),"",VLOOKUP(J70,RELACIONES!$B$3:$E$83,4,FALSE)*E70) -> 2341.372
A71: Revoque grueso + revoque fino (e grueso=2 cm) | B71: m2 | C71: FRATACHO (U) | D71: U | E71: 0.007 | F71: Albañilería | G71: Revoques | H71: SI | I71: =IF(ISBLANK(A71),"",VLOOKUP(A71,RELACIONES!$G$3:$H$65,2,FALSE())) -> Revoques 2 en 1: grueso y fino interior | J71: =IF(ISBLANK(A71),"",VLOOKUP(C71,RELACIONES!$A$3:$B$70,2,FALSE)) -> FRATACHO (U) | K71: =IF(ISBLANK(A71),"",VLOOKUP(J71,RELACIONES!$B$3:$E$83,4,FALSE)*E71) -> 24.5
A72: Revoque grueso + revoque fino (e grueso=2 cm) | B72: m2 | C72: FRATACHO ABRASIVO (U) | D72: U | E72: 0.013 | F72: Albañilería | G72: Revoques | H72: SI | I72: =IF(ISBLANK(A72),"",VLOOKUP(A72,RELACIONES!$G$3:$H$65,2,FALSE())) -> Revoques 2 en 1: grueso y fino interior | J72: =IF(ISBLANK(A72),"",VLOOKUP(C72,RELACIONES!$A$3:$B$70,2,FALSE)) -> FRATACHO ABRASIVO (U) | K72: =IF(ISBLANK(A72),"",VLOOKUP(J72,RELACIONES!$B$3:$E$83,4,FALSE)*E72) -> 58.5
A73: Revoque grueso + revoque fino (e grueso=2 cm) | B73: m2 | C73: LLANA LISA (U) | D73: U | E73: 0.007 | F73: Albañilería | G73: Revoques | H73: SI | I73: =IF(ISBLANK(A73),"",VLOOKUP(A73,RELACIONES!$G$3:$H$65,2,FALSE())) -> Revoques 2 en 1: grueso y fino interior | J73: =IF(ISBLANK(A73),"",VLOOKUP(C73,RELACIONES!$A$3:$B$70,2,FALSE)) -> LLANA LISA (U) | K73: =IF(ISBLANK(A73),"",VLOOKUP(J73,RELACIONES!$B$3:$E$83,4,FALSE)*E73) -> 73.5
A74: Revoque grueso + revoque fino (e grueso=2 cm) | B74: m2 | C74: DISCO DE CORTE PARA MAMPOSTERÍA (U) | D74: U | E74: 0.025 | F74: Albañilería | G74: Revoques | H74: SI | I74: =IF(ISBLANK(A74),"",VLOOKUP(A74,RELACIONES!$G$3:$H$65,2,FALSE())) -> Revoques 2 en 1: grueso y fino interior | J74: =IF(ISBLANK(A74),"",VLOOKUP(C74,RELACIONES!$A$3:$B$70,2,FALSE)) -> DISCO DE CORTE PARA MAMPOSTERÍA (U) | K74: =IF(ISBLANK(A74),"",VLOOKUP(J74,RELACIONES!$B$3:$E$83,4,FALSE)*E74) -> 100
I75: =IF(ISBLANK(A75),"",VLOOKUP(A75,RELACIONES!$G$3:$H$65,2,FALSE())) | J75: =IF(ISBLANK(A75),"",VLOOKUP(C75,RELACIONES!$A$3:$B$70,2,FALSE)) | K75: =IF(ISBLANK(A75),"",VLOOKUP(J75,RELACIONES!$B$3:$E$83,4,FALSE)*E75)
A76: Revoque grueso + revoque fino c/hidrófugo (e grueso=2 cm) | B76: m2 | C76: CEMENTO ALBAÑILERÍA (KG) | D76: KG | E76: 9.08 | F76: Albañilería | G76: Revoques | H76: NO | I76: =IF(ISBLANK(A76),"",VLOOKUP(A76,RELACIONES!$G$3:$H$65,2,FALSE())) -> Revoques 3 en 1: grueso con hidrofugo y fino exterior | J76: =IF(ISBLANK(A76),"",VLOOKUP(C76,RELACIONES!$A$3:$B$70,2,FALSE)) -> Cemento Loma Negra | K76: =IF(ISBLANK(A76),"",VLOOKUP(J76,RELACIONES!$B$3:$E$83,4,FALSE)*E76) -> 2840.8596
A77: Revoque grueso + revoque fino c/hidrófugo (e grueso=2 cm) | B77: m2 | C77: ARENA (M3) | D77: M3 | E77: 0.024 | F77: Albañilería | G77: Revoques | H77: NO | I77: =IF(ISBLANK(A77),"",VLOOKUP(A77,RELACIONES!$G$3:$H$65,2,FALSE())) -> Revoques 3 en 1: grueso con hidrofugo y fino exterior | J77: =IF(ISBLANK(A77),"",VLOOKUP(C77,RELACIONES!$A$3:$B$70,2,FALSE)) -> Arena fina | K77: =IF(ISBLANK(A77),"",VLOOKUP(J77,RELACIONES!$B$3:$E$83,4,FALSE)*E77) -> 1306.8398
A78: Revoque grueso + revoque fino c/hidrófugo (e grueso=2 cm) | B78: m2 | C78: HIDRÓFUGO EN PASTA (KG) | D78: KG | E78: 0.36 | F78: Albañilería | G78: Revoques | H78: NO | I78: =IF(ISBLANK(A78),"",VLOOKUP(A78,RELACIONES!$G$3:$H$65,2,FALSE())) -> Revoques 3 en 1: grueso con hidrofugo y fino exterior | J78: =IF(ISBLANK(A78),"",VLOOKUP(C78,RELACIONES!$A$3:$B$70,2,FALSE)) -> Hidrófugo Sika, caja x 20kg | K78: =IF(ISBLANK(A78),"",VLOOKUP(J78,RELACIONES!$B$3:$E$83,4,FALSE)*E78) -> 880.66836
A79: Revoque grueso + revoque fino c/hidrófugo (e grueso=2 cm) | B79: m2 | C79: CAL AÉREA (KG) | D79: KG | E79: 2.2 | F79: Albañilería | G79: Revoques | H79: NO | I79: =IF(ISBLANK(A79),"",VLOOKUP(A79,RELACIONES!$G$3:$H$65,2,FALSE())) -> Revoques 3 en 1: grueso con hidrofugo y fino exterior | J79: =IF(ISBLANK(A79),"",VLOOKUP(C79,RELACIONES!$A$3:$B$70,2,FALSE)) -> Cal Aérea Hidratada El Milagro | K79: =IF(ISBLANK(A79),"",VLOOKUP(J79,RELACIONES!$B$3:$E$83,4,FALSE)*E79) -> 2341.372
A80: Revoque grueso + revoque fino c/hidrófugo (e grueso=2 cm) | B80: m2 | C80: FRATACHO (U) | D80: U | E80: 0.007 | F80: Albañilería | G80: Revoques | H80: SI | I80: =IF(ISBLANK(A80),"",VLOOKUP(A80,RELACIONES!$G$3:$H$65,2,FALSE())) -> Revoques 3 en 1: grueso con hidrofugo y fino exterior | J80: =IF(ISBLANK(A80),"",VLOOKUP(C80,RELACIONES!$A$3:$B$70,2,FALSE)) -> FRATACHO (U) | K80: =IF(ISBLANK(A80),"",VLOOKUP(J80,RELACIONES!$B$3:$E$83,4,FALSE)*E80) -> 24.5
A81: Revoque grueso + revoque fino c/hidrófugo (e grueso=2 cm) | B81: m2 | C81: FRATACHO ABRASIVO (U) | D81: U | E81: 0.013 | F81: Albañilería | G81: Revoques | H81: SI | I81: =IF(ISBLANK(A81),"",VLOOKUP(A81,RELACIONES!$G$3:$H$65,2,FALSE())) -> Revoques 3 en 1: grueso con hidrofugo y fino exterior | J81: =IF(ISBLANK(A81),"",VLOOKUP(C81,RELACIONES!$A$3:$B$70,2,FALSE)) -> FRATACHO ABRASIVO (U) | K81: =IF(ISBLANK(A81),"",VLOOKUP(J81,RELACIONES!$B$3:$E$83,4,FALSE)*E81) -> 58.5
A82: Revoque grueso + revoque fino c/hidrófugo (e grueso=2 cm) | B82: m2 | C82: LLANA LISA (U) | D82: U | E82: 0.007 | F82: Albañilería | G82: Revoques | H82: SI | I82: =IF(ISBLANK(A82),"",VLOOKUP(A82,RELACIONES!$G$3:$H$65,2,FALSE())) -> Revoques 3 en 1: grueso con hidrofugo y fino exterior | J82: =IF(ISBLANK(A82),"",VLOOKUP(C82,RELACIONES!$A$3:$B$70,2,FALSE)) -> LLANA LISA (U) | K82: =IF(ISBLANK(A82),"",VLOOKUP(J82,RELACIONES!$B$3:$E$83,4,FALSE)*E82) -> 73.5
A83: Revoque grueso + revoque fino c/hidrófugo (e grueso=2 cm) | B83: m2 | C83: DISCO DE CORTE PARA MAMPOSTERÍA (U) | D83: U | E83: 0.025 | F83: Albañilería | G83: Revoques | H83: SI | I83: =IF(ISBLANK(A83),"",VLOOKUP(A83,RELACIONES!$G$3:$H$65,2,FALSE())) -> Revoques 3 en 1: grueso con hidrofugo y fino exterior | J83: =IF(ISBLANK(A83),"",VLOOKUP(C83,RELACIONES!$A$3:$B$70,2,FALSE)) -> DISCO DE CORTE PARA MAMPOSTERÍA (U) | K83: =IF(ISBLANK(A83),"",VLOOKUP(J83,RELACIONES!$B$3:$E$83,4,FALSE)*E83) -> 100
I84: =IF(ISBLANK(A84),"",VLOOKUP(A84,RELACIONES!$G$3:$H$65,2,FALSE())) | J84: =IF(ISBLANK(A84),"",VLOOKUP(C84,RELACIONES!$A$3:$B$70,2,FALSE)) | K84: =IF(ISBLANK(A84),"",VLOOKUP(J84,RELACIONES!$B$3:$E$83,4,FALSE)*E84)
A85: Revoque grueso + enlucido de yeso (e grueso=2 cm) | B85: m2 | C85: CEMENTO ALBAÑILERÍA (KG) | D85: KG | E85: 2.52 | F85: Albañilería | G85: Revoques | H85: NO | I85: =IF(ISBLANK(A85),"",VLOOKUP(A85,RELACIONES!$G$3:$H$65,2,FALSE())) -> Revoques 3 en 1: grueso con hidrofugo y fino exterior | J85: =IF(ISBLANK(A85),"",VLOOKUP(C85,RELACIONES!$A$3:$B$70,2,FALSE)) -> Cemento Loma Negra | K85: =IF(ISBLANK(A85),"",VLOOKUP(J85,RELACIONES!$B$3:$E$83,4,FALSE)*E85) -> 788.4324
A86: Revoque grueso + enlucido de yeso (e grueso=2 cm) | B86: m2 | C86: ARENA (M3) | D86: M3 | E86: 0.024 | F86: Albañilería | G86: Revoques | H86: NO | I86: =IF(ISBLANK(A86),"",VLOOKUP(A86,RELACIONES!$G$3:$H$65,2,FALSE())) -> Revoques 3 en 1: grueso con hidrofugo y fino exterior | J86: =IF(ISBLANK(A86),"",VLOOKUP(C86,RELACIONES!$A$3:$B$70,2,FALSE)) -> Arena fina | K86: =IF(ISBLANK(A86),"",VLOOKUP(J86,RELACIONES!$B$3:$E$83,4,FALSE)*E86) -> 1306.8398
A87: Revoque grueso + enlucido de yeso (e grueso=2 cm) | B87: m2 | C87: CAL HIDRATADA (KG) | D87: KG | E87: 4.52 | F87: Albañilería | G87: Revoques | H87: NO | I87: =IF(ISBLANK(A87),"",VLOOKUP(A87,RELACIONES!$G$3:$H$65,2,FALSE())) -> Revoques 3 en 1: grueso con hidrofugo y fino exterior | J87: =IF(ISBLANK(A87),"",VLOOKUP(C87,RELACIONES!$A$3:$B$70,2,FALSE)) -> Cal Hidráulica, Hidralit Avellaneda | K87: =IF(ISBLANK(A87),"",VLOOKUP(J87,RELACIONES!$B$3:$E$83,4,FALSE)*E87) -> 1879.0996
A88: Revoque grueso + enlucido de yeso (e grueso=2 cm) | B88: m2 | C88: YESO (KG) | D88: KG | E88: 1.2 | F88: Albañilería | G88: Revoques | H88: NO | I88: =IF(ISBLANK(A88),"",VLOOKUP(A88,RELACIONES!$G$3:$H$65,2,FALSE())) -> Revoques 3 en 1: grueso con hidrofugo y fino exterior | J88: =IF(ISBLANK(A88),"",VLOOKUP(C88,RELACIONES!$A$3:$B$70,2,FALSE)) -> Yeso Blanco Betalfa Pescio x40kg | K88: =IF(ISBLANK(A88),"",VLOOKUP(J88,RELACIONES!$B$3:$E$83,4,FALSE)*E88) -> 1057.2045
A89: Revoque grueso + enlucido de yeso (e grueso=2 cm) | B89: m2 | C89: FRATACHO (U) | D89: U | E89: 0.007 | F89: Albañilería | G89: Revoques | H89: SI | I89: =IF(ISBLANK(A89),"",VLOOKUP(A89,RELACIONES!$G$3:$H$65,2,FALSE())) -> Revoques 3 en 1: grueso con hidrofugo y fino exterior | J89: =IF(ISBLANK(A89),"",VLOOKUP(C89,RELACIONES!$A$3:$B$70,2,FALSE)) -> FRATACHO (U) | K89: =IF(ISBLANK(A89),"",VLOOKUP(J89,RELACIONES!$B$3:$E$83,4,FALSE)*E89) -> 24.5
A90: Revoque grueso + enlucido de yeso (e grueso=2 cm) | B90: m2 | C90: LLANA LISA (U) | D90: U | E90: 0.007 | F90: Albañilería | G90: Revoques | H90: SI | I90: =IF(ISBLANK(A90),"",VLOOKUP(A90,RELACIONES!$G$3:$H$65,2,FALSE())) -> Revoques 3 en 1: grueso con hidrofugo y fino exterior | J90: =IF(ISBLANK(A90),"",VLOOKUP(C90,RELACIONES!$A$3:$B$70,2,FALSE)) -> LLANA LISA (U) | K90: =IF(ISBLANK(A90),"",VLOOKUP(J90,RELACIONES!$B$3:$E$83,4,FALSE)*E90) -> 73.5
A91: Revoque grueso + enlucido de yeso (e grueso=2 cm) | B91: m2 | C91: DISCO DE CORTE PARA MAMPOSTERÍA (U) | D91: U | E91: 0.025 | F91: Albañilería | G91: Revoques | H91: SI | I91: =IF(ISBLANK(A91),"",VLOOKUP(A91,RELACIONES!$G$3:$H$65,2,FALSE())) -> Revoques 3 en 1: grueso con hidrofugo y fino exterior | J91: =IF(ISBLANK(A91),"",VLOOKUP(C91,RELACIONES!$A$3:$B$70,2,FALSE)) -> DISCO DE CORTE PARA MAMPOSTERÍA (U) | K91: =IF(ISBLANK(A91),"",VLOOKUP(J91,RELACIONES!$B$3:$E$83,4,FALSE)*E91) -> 100
I92: =IF(ISBLANK(A92),"",VLOOKUP(A92,RELACIONES!$G$3:$H$65,2,FALSE())) | J92: =IF(ISBLANK(A92),"",VLOOKUP(C92,RELACIONES!$A$3:$B$70,2,FALSE)) | K92: =IF(ISBLANK(A92),"",VLOOKUP(J92,RELACIONES!$B$3:$E$83,4,FALSE)*E92)
A93: Revoque grueso + enlucido de yeso c/hidrófugo (e grueso=2 cm) | B93: m2 | C93: CEMENTO ALBAÑILERÍA (KG) | D93: KG | E93: 9.08 | F93: Albañilería | G93: Revoques | H93: NO | I93: =IF(ISBLANK(A93),"",VLOOKUP(A93,RELACIONES!$G$3:$H$65,2,FALSE())) -> Revoques Enlucido de yeso | J93: =IF(ISBLANK(A93),"",VLOOKUP(C93,RELACIONES!$A$3:$B$70,2,FALSE)) -> Cemento Loma Negra | K93: =IF(ISBLANK(A93),"",VLOOKUP(J93,RELACIONES!$B$3:$E$83,4,FALSE)*E93) -> 2840.8596
A94: Revoque grueso + enlucido de yeso c/hidrófugo (e grueso=2 cm) | B94: m2 | C94: ARENA (M3) | D94: M3 | E94: 0.024 | F94: Albañilería | G94: Revoques | H94: NO | I94: =IF(ISBLANK(A94),"",VLOOKUP(A94,RELACIONES!$G$3:$H$65,2,FALSE())) -> Revoques Enlucido de yeso | J94: =IF(ISBLANK(A94),"",VLOOKUP(C94,RELACIONES!$A$3:$B$70,2,FALSE)) -> Arena fina | K94: =IF(ISBLANK(A94),"",VLOOKUP(J94,RELACIONES!$B$3:$E$83,4,FALSE)*E94) -> 1306.8398
A95: Revoque grueso + enlucido de yeso c/hidrófugo (e grueso=2 cm) | B95: m2 | C95: HIDRÓFUGO EN PASTA (KG) | D95: KG | E95: 0.36 | F95: Albañilería | G95: Revoques | H95: NO | I95: =IF(ISBLANK(A95),"",VLOOKUP(A95,RELACIONES!$G$3:$H$65,2,FALSE())) -> Revoques Enlucido de yeso | J95: =IF(ISBLANK(A95),"",VLOOKUP(C95,RELACIONES!$A$3:$B$70,2,FALSE)) -> Hidrófugo Sika, caja x 20kg | K95: =IF(ISBLANK(A95),"",VLOOKUP(J95,RELACIONES!$B$3:$E$83,4,FALSE)*E95) -> 880.66836
A96: Revoque grueso + enlucido de yeso c/hidrófugo (e grueso=2 cm) | B96: m2 | C96: YESO (KG) | D96: KG | E96: 1.2 | F96: Albañilería | G96: Revoques | H96: NO | I96: =IF(ISBLANK(A96),"",VLOOKUP(A96,RELACIONES!$G$3:$H$65,2,FALSE())) -> Revoques Enlucido de yeso | J96: =IF(ISBLANK(A96),"",VLOOKUP(C96,RELACIONES!$A$3:$B$70,2,FALSE)) -> Yeso Blanco Betalfa Pescio x40kg | K96: =IF(ISBLANK(A96),"",VLOOKUP(J96,RELACIONES!$B$3:$E$83,4,FALSE)*E96) -> 1057.2045
A97: Revoque grueso + enlucido de yeso c/hidrófugo (e grueso=2 cm) | B97: m2 | C97: FRATACHO (U) | D97: U | E97: 0.007 | F97: Albañilería | G97: Revoques | H97: SI | I97: =IF(ISBLANK(A97),"",VLOOKUP(A97,RELACIONES!$G$3:$H$65,2,FALSE())) -> Revoques Enlucido de yeso | J97: =IF(ISBLANK(A97),"",VLOOKUP(C97,RELACIONES!$A$3:$B$70,2,FALSE)) -> FRATACHO (U) | K97: =IF(ISBLANK(A97),"",VLOOKUP(J97,RELACIONES!$B$3:$E$83,4,FALSE)*E97) -> 24.5
A98: Revoque grueso + enlucido de yeso c/hidrófugo (e grueso=2 cm) | B98: m2 | C98: LLANA LISA (U) | D98: U | E98: 0.007 | F98: Albañilería | G98: Revoques | H98: SI | I98: =IF(ISBLANK(A98),"",VLOOKUP(A98,RELACIONES!$G$3:$H$65,2,FALSE())) -> Revoques Enlucido de yeso | J98: =IF(ISBLANK(A98),"",VLOOKUP(C98,RELACIONES!$A$3:$B$70,2,FALSE)) -> LLANA LISA (U) | K98: =IF(ISBLANK(A98),"",VLOOKUP(J98,RELACIONES!$B$3:$E$83,4,FALSE)*E98) -> 73.5
A99: Revoque grueso + enlucido de yeso c/hidrófugo (e grueso=2 cm) | B99: m2 | C99: DISCO DE CORTE PARA MAMPOSTERÍA (U) | D99: U | E99: 0.025 | F99: Albañilería | G99: Revoques | H99: SI | I99: =IF(ISBLANK(A99),"",VLOOKUP(A99,RELACIONES!$G$3:$H$65,2,FALSE())) -> Revoques Enlucido de yeso | J99: =IF(ISBLANK(A99),"",VLOOKUP(C99,RELACIONES!$A$3:$B$70,2,FALSE)) -> DISCO DE CORTE PARA MAMPOSTERÍA (U) | K99: =IF(ISBLANK(A99),"",VLOOKUP(J99,RELACIONES!$B$3:$E$83,4,FALSE)*E99) -> 100
I100: =IF(ISBLANK(A100),"",VLOOKUP(A100,RELACIONES!$G$3:$H$65,2,FALSE())) | J100: =IF(ISBLANK(A100),"",VLOOKUP(C100,RELACIONES!$A$3:$B$70,2,FALSE)) | K100: =IF(ISBLANK(A100),"",VLOOKUP(J100,RELACIONES!$B$3:$E$83,4,FALSE)*E100)
A101: Engrosado de yeso + enlucido de yeso (e engrosado=2 cm) | B101: m2 | C101: YESO (KG) | D101: KG | E101: 10.2 | F101: Albañilería | G101: Revoques | H101: NO | I101: =IF(ISBLANK(A101),"",VLOOKUP(A101,RELACIONES!$G$3:$H$65,2,FALSE())) -> Revoques Enlucido de yeso | J101: =IF(ISBLANK(A101),"",VLOOKUP(C101,RELACIONES!$A$3:$B$70,2,FALSE)) -> Yeso Blanco Betalfa Pescio x40kg | K101: =IF(ISBLANK(A101),"",VLOOKUP(J101,RELACIONES!$B$3:$E$83,4,FALSE)*E101) -> 8986.2383
...

Sheet RELACIONES
A3: LADRILLOS HUECOS DE 8 CM (U) | B3: Ladrillo Hueco 8x18x33 Loimar | C3: =VLOOKUP(B3,'📦 Materiales'!$C$3:$D$1402,2,FALSE) -> Unidad | D3: 1 | E3: =VLOOKUP(B3,'📦 Materiales'!$C$3:$E$1402,3,FALSE)/D3 -> 783.99 | G3: Retiro de revestimientos en pared | H3: Demoliciones Picado de revestimiento | I3: =VLOOKUP(H3,'🔨 Mano de Obra'!$H$4:$I$475,2,FALSE) -> 31742.08
A4: CEMENTO ALBAÑILERÍA (KG) | B4: Cemento Loma Negra | C4: =VLOOKUP(B4,'📦 Materiales'!$C$3:$D$1402,2,FALSE) -> Kilogramo | D4: 1 | E4: =VLOOKUP(B4,'📦 Materiales'!$C$3:$E$1402,3,FALSE)/D4 -> 312.87 | G4: Retiro de pisos | H4: Demoliciones De pisos | I4: =VLOOKUP(H4,'🔨 Mano de Obra'!$H$4:$I$475,2,FALSE) -> 33218.38
A5: ARENA (M3) | B5: Arena fina | C5: =VLOOKUP(B5,'📦 Materiales'!$C$3:$D$1402,2,FALSE) -> Metro cùbico | D5: 1 | E5: =VLOOKUP(B5,'📦 Materiales'!$C$3:$E$1402,3,FALSE)/D5 -> 54451.66 | G5: Picado de revoque | H5: Demoliciones Picado de revoques | I5: =VLOOKUP(H5,'🔨 Mano de Obra'!$H$4:$I$475,2,FALSE) -> 41830.57
A6: CAL HIDRATADA (KG) | B6: Cal Hidráulica, Hidralit Avellaneda | C6: =VLOOKUP(B6,'📦 Materiales'!$C$3:$D$1402,2,FALSE) -> Kilogramo | D6: 1 | E6: =VLOOKUP(B6,'📦 Materiales'!$C$3:$E$1402,3,FALSE)/D6 -> 415.73 | G6: Demolicion de pared | H6: Demoliciones De mamposterías | I6: =VLOOKUP(H6,'🔨 Mano de Obra'!$H$4:$I$475,2,FALSE) -> 40231.176
A7: HIERRO ADN Ø6MM (ML) | B7: Hierro Torsionado del 6 mm | C7: =VLOOKUP(B7,'📦 Materiales'!$C$3:$D$1402,2,FALSE) -> Unidad | D7: 1 | E7: =VLOOKUP(B7,'📦 Materiales'!$C$3:$E$1402,3,FALSE)/D7 -> 9535.65 | G7: Tabique de ladrillos hueco de 8x18x33 | H7: Mampostería de elevación con cemento tradicional Ladrillos huecos 08x18x33 | I7: =VLOOKUP(H7,'🔨 Mano de Obra'!$H$4:$I$475,2,FALSE) -> 14953.21
A8: DISCO DE CORTE PARA MAMPOSTERÍA (U) | B8: DISCO DE CORTE PARA MAMPOSTERÍA (U) | C8: =VLOOKUP(B8,'📦 Materiales'!$C$3:$D$1402,2,FALSE) -> Unidad | D8: 1 | E8: =VLOOKUP(B8,'📦 Materiales'!$C$3:$E$1402,3,FALSE)/D8 -> 4000 | G8: Tabique de ladrillos hueco de 12x18x33 | H8: Mampostería de elevación con cemento tradicional Ladrillos huecos 12x18x33 | I8: =VLOOKUP(H8,'🔨 Mano de Obra'!$H$4:$I$475,2,FALSE) -> 18247.95
A9: LADRILLOS HUECOS DE 12 CM (U) | B9: Ladrillo Hueco 12x18x33 Loimar | C9: =VLOOKUP(B9,'📦 Materiales'!$C$3:$D$1402,2,FALSE) -> Unidad | D9: 1 | E9: =VLOOKUP(B9,'📦 Materiales'!$C$3:$E$1402,3,FALSE)/D9 -> 1026.65 | G9: Banquina (e=10 cm) | H9: Contrapisos De cascotes s/ terreno natural. Esp: 10cm. (con cemento de albañilería) | I9: =VLOOKUP(H9,'🔨 Mano de Obra'!$H$4:$I$475,2,FALSE) -> 18085.58
A10: CASCOTE DE LADRILLOS (M3) | B10: CASCOTE DE LADRILLOS (M3) | C10: =VLOOKUP(B10,'📦 Materiales'!$C$3:$D$1402,2,FALSE) -> Metro cubico | D10: 1 | E10: =VLOOKUP(B10,'📦 Materiales'!$C$3:$E$1402,3,FALSE)/D10 -> 27000 | G10: Contrapiso de cascote sobre losa (e=10 cm) | H10: Contrapisos De cascotes s/ terreno natural. Esp: 10cm. (con cemento de albañilería) | I10: =VLOOKUP(H10,'🔨 Mano de Obra'!$H$4:$I$475,2,FALSE) -> 18085.58
A11: FRATACHO (U) | B11: FRATACHO (U) | C11: =VLOOKUP(B11,'📦 Materiales'!$C$3:$D$1402,2,FALSE) -> Unidad | D11: 1 | E11: =VLOOKUP(B11,'📦 Materiales'!$C$3:$E$1402,3,FALSE)/D11 -> 3500 | G11: Membrana asfáltica sin aluminio | H11: Cubiertas Colocación de membrana asfáltica con imprimación de superficie | I11: =VLOOKUP(H11,'🔨 Mano de Obra'!$H$4:$I$475,2,FALSE) -> 17129.59
A12: LLANA LISA (U) | B12: LLANA LISA (U) | C12: =VLOOKUP(B12,'📦 Materiales'!$C$3:$D$1402,2,FALSE) -> Unidad | D12: 1 | E12: =VLOOKUP(B12,'📦 Materiales'!$C$3:$E$1402,3,FALSE)/D12 -> 10500 | G12: Membrana asfáltica con aluminio | H12: Cubiertas Colocación de membrana asfáltica con imprimación de superficie | I12: =VLOOKUP(H12,'🔨 Mano de Obra'!$H$4:$I$475,2,FALSE) -> 17129.59
A13: CARTÓN CORRUGADO (M2) | B13: CARTÓN CORRUGADO (M2) | C13: =VLOOKUP(B13,'📦 Materiales'!$C$3:$D$1402,2,FALSE) -> Metro cuadrado | D13: 1 | E13: =VLOOKUP(B13,'📦 Materiales'!$C$3:$E$1402,3,FALSE)/D13 -> 520 | G13: Membrana asfáltica geotextil | H13: Cubiertas Colocación de membrana asfáltica con imprimación de superficie | I13: =VLOOKUP(H13,'🔨 Mano de Obra'!$H$4:$I$475,2,FALSE) -> 17129.59
A14: MEMBRANA ASFÁLTICA SIN ALUMINIO (M2) | B14: Membrana Asfáltica c/aluminio Megaflex esp. 4mm | C14: =VLOOKUP(B14,'📦 Materiales'!$C$3:$D$1402,2,FALSE) -> Metro cuadrado | D14: 1 | E14: =VLOOKUP(B14,'📦 Materiales'!$C$3:$E$1402,3,FALSE)/D14 -> 11592.02 | G14: Pintura asfáltica base acuosa | I14: =VLOOKUP(H14,'🔨 Mano de Obra'!$H$4:$I$475,2,FALSE) -> #N/A
A15: MEMBRANA ASFÁLTICA CON ALUMINIO (M2) | B15: Membrana Asfáltica c/aluminio Megaflex esp. 4mm | C15: =VLOOKUP(B15,'📦 Materiales'!$C$3:$D$1402,2,FALSE) -> Metro cuadrado | D15: 1 | E15: =VLOOKUP(B15,'📦 Materiales'!$C$3:$E$1402,3,FALSE)/D15 -> 11592.02 | G15: Pintura asfáltica base solvente | I15: =VLOOKUP(H15,'🔨 Mano de Obra'!$H$4:$I$475,2,FALSE) -> #N/A
A16: MEMBRANA ASFÁLTICA GEOTEXTIL (M2) | B16: MEMBRANA ASFÁLTICA GEOTEXTIL (M2) | C16: =VLOOKUP(B16,'📦 Materiales'!$C$3:$D$1402,2,FALSE) -> Metro cuadrado | D16: 1 | E16: =VLOOKUP(B16,'📦 Materiales'!$C$3:$E$1402,3,FALSE)/D16 -> 8000 | G16: Film polietileno 200µ | I16: =VLOOKUP(H16,'🔨 Mano de Obra'!$H$4:$I$475,2,FALSE) -> #N/A
A17: PINTURA ASFÁLTICA ACUOSA (KG) | B17: Pintura asfáltica Megaflex, base solvente, 18L | C17: =VLOOKUP(B17,'📦 Materiales'!$C$3:$D$1402,2,FALSE) -> Unidad | D17: 18 | E17: =VLOOKUP(B17,'📦 Materiales'!$C$3:$E$1402,3,FALSE)/D17 -> 9483.3217 | G17: Carpeta de cemento 1:3 (e=2 cm) | H17: Carpetas Alisado de cemento para piso (Esp:2cm) | I17: =VLOOKUP(H17,'🔨 Mano de Obra'!$H$4:$I$475,2,FALSE) -> 16793.73
A18: PINTURA ASFÁLTICA SOLVENTE (KG) | B18: Pintura asfáltica Megaflex, base solvente, 18L | C18: =VLOOKUP(B18,'📦 Materiales'!$C$3:$D$1402,2,FALSE) -> Unidad | D18: 18 | E18: =VLOOKUP(B18,'📦 Materiales'!$C$3:$E$1402,3,FALSE)/D18 -> 9483.3217 | G18: Carpeta de cemento 1:3 c/hidrófugo (e=2 cm) | H18: Carpetas Hidrofuga s/contrapiso (Esp: 2cm) | I18: =VLOOKUP(H18,'🔨 Mano de Obra'!$H$4:$I$475,2,FALSE) -> 15243.57
A19: FILM POLIETILENO 200µ (M2) | B19: FILM POLIETILENO 200µ (M2) | C19: =VLOOKUP(B19,'📦 Materiales'!$C$3:$D$1402,2,FALSE) -> Metro cuadrado | D19: 1 | E19: =VLOOKUP(B19,'📦 Materiales'!$C$3:$E$1402,3,FALSE)/D19 -> 800 | G19: Revoque grueso + revoque fino (e grueso=2 cm) | H19: Revoques 2 en 1: grueso y fino interior | I19: =VLOOKUP(H19,'🔨 Mano de Obra'!$H$4:$I$475,2,FALSE) -> 20275.51
A20: FRATACHO ABRASIVO (U) | B20: FRATACHO ABRASIVO (U) | C20: =VLOOKUP(B20,'📦 Materiales'!$C$3:$D$1402,2,FALSE) -> Unidad | D20: 1 | E20: =VLOOKUP(B20,'📦 Materiales'!$C$3:$E$1402,3,FALSE)/D20 -> 4500 | G20: Revoque grueso + revoque fino c/hidrófugo (e grueso=2 cm) | H20: Revoques 3 en 1: grueso con hidrofugo y fino exterior | I20: =VLOOKUP(H20,'🔨 Mano de Obra'!$H$4:$I$475,2,FALSE) -> 22809.94
A21: HIDRÓFUGO EN PASTA (KG) | B21: Hidrófugo Sika, caja x 20kg | C21: =VLOOKUP(B21,'📦 Materiales'!$C$3:$D$1402,2,FALSE) -> Unidad | D21: 20 | E21: =VLOOKUP(B21,'📦 Materiales'!$C$3:$E$1402,3,FALSE)/D21 -> 2446.301 | G21: Revoque grueso + enlucido de yeso (e grueso=2 cm) | H21: Revoques 3 en 1: grueso con hidrofugo y fino exterior | I21: =VLOOKUP(H21,'🔨 Mano de Obra'!$H$4:$I$475,2,FALSE) -> 22809.94
A22: CAL AÉREA (KG) | B22: Cal Aérea Hidratada El Milagro | C22: =VLOOKUP(B22,'📦 Materiales'!$C$3:$D$1402,2,FALSE) -> Kilogramo | D22: 1 | E22: =VLOOKUP(B22,'📦 Materiales'!$C$3:$E$1402,3,FALSE)/D22 -> 1064.26 | G22: Revoque grueso + enlucido de yeso c/hidrófugo (e grueso=2 cm) | H22: Revoques Enlucido de yeso | I22: =VLOOKUP(H22,'🔨 Mano de Obra'!$H$4:$I$475,2,FALSE) -> 15206.65
A23: YESO (KG) | B23: Yeso Blanco Betalfa Pescio x40kg | C23: =VLOOKUP(B23,'📦 Materiales'!$C$3:$D$1402,2,FALSE) -> Unidad | D23: 40 | E23: =VLOOKUP(B23,'📦 Materiales'!$C$3:$E$1402,3,FALSE)/D23 -> 881.00375 | G23: Engrosado de yeso + enlucido de yeso (e engrosado=2 cm) | H23: Revoques Enlucido de yeso | I23: =VLOOKUP(H23,'🔨 Mano de Obra'!$H$4:$I$475,2,FALSE) -> 15206.65
A24: SIKACERAM FLEXIBLE (KG) | B24: Pegamento para porcellanato x 30kg. Klaukol | C24: =VLOOKUP(B24,'📦 Materiales'!$C$3:$D$1402,2,FALSE) -> Unidad | D24: 30 | E24: =VLOOKUP(B24,'📦 Materiales'!$C$3:$E$1402,3,FALSE)/D24 -> 1375.8283 | G24: Cerámica en piso c/Sikaceram Flexible | H24: Pisos Cerámico, Porcellanato y Loseta Cerámico 60x60 | I24: =VLOOKUP(H24,'🔨 Mano de Obra'!$H$4:$I$475,2,FALSE) -> 34214.93
A25: PASTINA (KG) | B25: Pastina para Porcellanato Klaukol | C25: =VLOOKUP(B25,'📦 Materiales'!$C$3:$D$1402,2,FALSE) -> Kilogramo | D25: 1 | E25: =VLOOKUP(B25,'📦 Materiales'!$C$3:$E$1402,3,FALSE)/D25 -> 4494.42 | G25: Cerámica en piso c/Sikaceram Impermeable | H25: Pisos Cerámico, Porcellanato y Loseta Cerámico 60x60 | I25: =VLOOKUP(H25,'🔨 Mano de Obra'!$H$4:$I$475,2,FALSE) -> 34214.93
A26: SEPARADORES PORCELANATOS TIPO CUÑA (U) | B26: SEPARADORES PORCELANATOS TIPO CUÑA (U) | C26: =VLOOKUP(B26,'📦 Materiales'!$C$3:$D$1402,2,FALSE) -> Unidad | D26: 1 | E26: =VLOOKUP(B26,'📦 Materiales'!$C$3:$E$1402,3,FALSE)/D26 -> 76 | G26: Porcelanato en piso c/Sikaceram Flexible | H26: Pisos Cerámico, Porcellanato y Loseta Porcellanato 60x60 | I26: =VLOOKUP(H26,'🔨 Mano de Obra'!$H$4:$I$475,2,FALSE) -> 38016.63
A27: LLANA DENTADA 10MM (U) | B27: LLANA DENTADA 10MM (U) | C27: =VLOOKUP(B27,'📦 Materiales'!$C$3:$D$1402,2,FALSE) -> Unidad | D27: 1 | E27: =VLOOKUP(B27,'📦 Materiales'!$C$3:$E$1402,3,FALSE)/D27 -> 12300 | G27: Porcelanato en piso c/Sikaceram Impermeable | H27: Pisos Cerámico, Porcellanato y Loseta Porcellanato 60x60 | I27: =VLOOKUP(H27,'🔨 Mano de Obra'!$H$4:$I$475,2,FALSE) -> 38016.63
A28: CINTA DE ENMASCARAR (ML) | B28: Cinta Papel encubrir 18 mm. x 50 mts | C28: =VLOOKUP(B28,'📦 Materiales'!$C$3:$D$1402,2,FALSE) -> Unidad | D28: 50 | E28: =VLOOKUP(B28,'📦 Materiales'!$C$3:$E$1402,3,FALSE)/D28 -> 115.0668 | G28: Cerámica en pared c/Sikaceram Flexible | H28: Revestimientos Cerámico, Porcellanato, Venecita y Refractario Cerámico 60x60 | I28: =VLOOKUP(H28,'🔨 Mano de Obra'!$H$4:$I$475,2,FALSE) -> 44378.05
... A30: DISCO DIAMANTADO PARA PORCELANATO (U) | B30: DISCO DIAMANTADO PARA PORCELANATO (U) | C30: =VLOOKUP(B30,'📦 Materiales'!$C$3:$D$1402,2,FALSE) -> Unidad | D30: 1 | E30: =VLOOKUP(B30,'📦 Materiales'!$C$3:$E$1402,3,FALSE)/D30 -> 24000 | G30: Porcelanato en pared c/Sikaceram Flexible | H30: Revestimientos Cerámico, Porcellanato, Venecita y Refractario Porcellanato 60x60 | I30: =VLOOKUP(H30,'🔨 Mano de Obra'!$H$4:$I$475,2,FALSE) -> 52209.47
A31: PLACA DE YESO 9.5 MM (M2) | B31: Placa yeso Durlock 9.5mm Std. 1.20 x 2.40 mts. | C31: =VLOOKUP(B31,'📦 Materiales'!$C$3:$D$1402,2,FALSE) -> Unidad | D31: =1.2*2.4 -> 2.88 | E31: =VLOOKUP(B31,'📦 Materiales'!$C$3:$E$1402,3,FALSE)/D31 -> 6007.3889 | G31: Porcelanato en pared c/Sikaceram Impermeable | H31: Revestimientos Cerámico, Porcellanato, Venecita y Refractario Porcellanato 60x60 | I31: =VLOOKUP(H31,'🔨 Mano de Obra'!$H$4:$I$475,2,FALSE) -> 52209.47
A32: MONTANTE 69MM (ML) | B32: Montante de 69mm x 2.60mts | C32: =VLOOKUP(B32,'📦 Materiales'!$C$3:$D$1402,2,FALSE) -> Unidad | D32: 2.6 | E32: =VLOOKUP(B32,'📦 Materiales'!$C$3:$E$1402,3,FALSE)/D32 -> 2383.7192 | G32: Tabique simple con montantes cada 40cm – sin aislación | H32: Construcción en Seco Tabique espesor 9.5cm | I32: =VLOOKUP(H32,'🔨 Mano de Obra'!$H$4:$I$475,2,FALSE) -> 28149.49
A33: SOLERA 70MM (ML) | B33: Solera de 70mm x 2.60 mts. | C33: =VLOOKUP(B33,'📦 Materiales'!$C$3:$D$1402,2,FALSE) -> Unidad | D33: 2.6 | E33: =VLOOKUP(B33,'📦 Materiales'!$C$3:$E$1402,3,FALSE)/D33 -> 3653.3692 | G33: Tabique simple con montantes cada 40cm – con rollo de lana de vidrio | H33: Construcción en Seco Tabique espesor 9.5cm c/aislación acústica | I33: =VLOOKUP(H33,'🔨 Mano de Obra'!$H$4:$I$475,2,FALSE) -> 29429.01
A34: CANTONERAS (ML/ML DE VANO) | B34: Cantonera Durlock Metal Galvanizado x 2,60 m | C34: =VLOOKUP(B34,'📦 Materiales'!$C$3:$D$1402,2,FALSE) -> Unidad | D34: 2.6 | E34: =VLOOKUP(B34,'📦 Materiales'!$C$3:$E$1402,3,FALSE)/D34 -> 1330.8808 | G34: Tabique doble exterior con montantes cada 40cm – con rollo de lana de vidrio y placa anti humedad de un lado | H34: Construcción en Seco Tabique espesor 9.5cm c/aislación acústica | I34: =VLOOKUP(H34,'🔨 Mano de Obra'!$H$4:$I$475,2,FALSE) -> 29429.01
A35: TORNILLOS TIPO T1 (U) | B35: Tornillo Auto-Perforante T2 Punta Aguja 6 x 1 | C35: =VLOOKUP(B35,'📦 Materiales'!$C$3:$D$1402,2,FALSE) -> Unidad | D35: 1 | E35: =VLOOKUP(B35,'📦 Materiales'!$C$3:$E$1402,3,FALSE)/D35 -> 28.6 | G35: Tabique doble con montantes cada 40cm – con rollo de lana de vidrio y placa anti humedad de un lado | H35: Construcción en Seco Tabique espesor 9.5cm c/aislación acústica | I35: =VLOOKUP(H35,'🔨 Mano de Obra'!$H$4:$I$475,2,FALSE) -> 29429.01
A36: TORNILLOS TIPO T2 (U) | B36: Tornillo Auto-Perforante T2 Punta Aguja 6 x 1 | C36: =VLOOKUP(B36,'📦 Materiales'!$C$3:$D$1402,2,FALSE) -> Unidad | D36: 1 | E36: =VLOOKUP(B36,'📦 Materiales'!$C$3:$E$1402,3,FALSE)/D36 -> 28.6 | G36: Cielorraso junta tomada estructura 35mm – sin aislación | H36: Construcción en Seco Cielorraso con placas de yeso | I36: =VLOOKUP(H36,'🔨 Mano de Obra'!$H$4:$I$475,2,FALSE) -> 25078.64
A37: FIJACIONES (U) | B37: FIJACIONES (U) | C37: =VLOOKUP(B37,'📦 Materiales'!$C$3:$D$1402,2,FALSE) -> Unidad | D37: 1 | E37: =VLOOKUP(B37,'📦 Materiales'!$C$3:$E$1402,3,FALSE)/D37 -> 232 | G37: Cielorraso junta tomada estructura 35mm – con rollo de lana de vidrio | H37: Construcción en Seco Cielorraso con placas de yeso | I37: =VLOOKUP(H37,'🔨 Mano de Obra'!$H$4:$I$475,2,FALSE) -> 25078.64
A38: CINTA DE PAPEL (ML) | B38: Cinta de papel x 76mm - Durlock (rollo de 150 ml) | C38: =VLOOKUP(B38,'📦 Materiales'!$C$3:$D$1402,2,FALSE) -> Metro lineal | D38: 150 | E38: =VLOOKUP(B38,'📦 Materiales'!$C$3:$E$1402,3,FALSE)/D38 -> 1.6962 | G38: Enduido plástico interior mate (2 manos) | H38: Pinturas Paredes interiores | I38: =VLOOKUP(H38,'🔨 Mano de Obra'!$H$4:$I$475,2,FALSE) -> 12800.17
A39: MASILLA (KG) | B39: Masilla Durlock (Lista Para Usar) | C39: =VLOOKUP(B39,'📦 Materiales'!$C$3:$D$1402,2,FALSE) -> Kilogramo | D39: 1 | E39: =VLOOKUP(B39,'📦 Materiales'!$C$3:$E$1402,3,FALSE)/D39 -> 3321.79 | G39: Látex interior mate (3 manos) | H39: Pinturas Paredes interiores | I39: =VLOOKUP(H39,'🔨 Mano de Obra'!$H$4:$I$475,2,FALSE) -> 12800.17
A40: LIJA (U) | B40: Lija | C40: =VLOOKUP(B40,'📦 Materiales'!$C$3:$D$1402,2,FALSE) -> Unidad | D40: 1 | E40: =VLOOKUP(B40,'📦 Materiales'!$C$3:$E$1402,3,FALSE)/D40 -> 1078.75 | G40: Látex interior satinado (3 manos) | H40: Pinturas Paredes interiores | I40: =VLOOKUP(H40,'🔨 Mano de Obra'!$H$4:$I$475,2,FALSE) -> 12800.17
A41: ROLLO LANA DE VIDRIO (M2) | B41: Aislante Lana de Vidrio Isover Rolac Plata Muro, esp 70 mm. | C41: =VLOOKUP(B41,'📦 Materiales'!$C$3:$D$1402,2,FALSE) -> Metro cuadrado | D41: 1 | E41: =VLOOKUP(B41,'📦 Materiales'!$C$3:$E$1402,3,FALSE)/D41 -> 25229.74 | G41: Látex exterior mate (3 manos) | H41: Pinturas Paredes exteriores | I41: =VLOOKUP(H41,'🔨 Mano de Obra'!$H$4:$I$475,2,FALSE) -> 13824.17
A42: PLACA DE YESO 12.5 MM ANTI HUMEDAD (M2) | B42: Placa Yeso Durlock RH 12.5 1.20 x 2.40 mts. (Resistente Humedad) | C42: =VLOOKUP(B42,'📦 Materiales'!$C$3:$D$1402,2,FALSE) -> Unidad | D42: =1.2*2.4 -> 2.88 | E42: =VLOOKUP(B42,'📦 Materiales'!$C$3:$E$1402,3,FALSE)/D42 -> 13546.076 | G42: Látex exterior satinado (3 manos) | H42: Pinturas Paredes exteriores | I42: =VLOOKUP(H42,'🔨 Mano de Obra'!$H$4:$I$475,2,FALSE) -> 13824.17
A43: PLACA DE YESO 12.5 MM (M2) | B43: Placa Yeso Durlock 12.5mm Std. 1.20 x 2.40 mts. | C43: =VLOOKUP(B43,'📦 Materiales'!$C$3:$D$1402,2,FALSE) -> Unidad | D43: =1.2*2.4 -> 2.88 | E43: =VLOOKUP(B43,'📦 Materiales'!$C$3:$E$1402,3,FALSE)/D43 -> 8716.6042 | G43: Esmalte sintético pared interior brillante (3 manos) | H43: Pinturas Esmalte sintético s/ abertura. | I43: =VLOOKUP(H43,'🔨 Mano de Obra'!$H$4:$I$475,2,FALSE) -> 20480.23
A44: MEMBRANA HIDROFUGA TIPO TYBEK (M2) | B44: MEMBRANA HIDROFUGA TIPO TYBEK (M2) | C44: =VLOOKUP(B44,'📦 Materiales'!$C$3:$D$1402,2,FALSE) -> Metro cuadrado | D44: 1 | E44: =VLOOKUP(B44,'📦 Materiales'!$C$3:$E$1402,3,FALSE)/D44 -> 5666.6667 | G44: Esmalte sintético pared interior satinado (3 manos) | H44: Pinturas Esmalte sintético s/ abertura. | I44: =VLOOKUP(H44,'🔨 Mano de Obra'!$H$4:$I$475,2,FALSE) -> 20480.23
A45: TORNILLOS TIPO T3 (U) | B45: Tornillo Auto-Perforante T3 Punta Aguja 6 x 11/2 | C45: =VLOOKUP(B45,'📦 Materiales'!$C$3:$D$1402,2,FALSE) -> Unidad | D45: 1 | E45: =VLOOKUP(B45,'📦 Materiales'!$C$3:$E$1402,3,FALSE)/D45 -> 63.64 | G45: Esmalte sintético sobre madera brillante (3 manos) | H45: Pinturas Esmalte sintético s/ abertura. | I45: =VLOOKUP(H45,'🔨 Mano de Obra'!$H$4:$I$475,2,FALSE) -> 20480.23
A46: MONTANTE 34MM (ML) | B46: Montante de 34mm x 2.60mts | C46: =VLOOKUP(B46,'📦 Materiales'!$C$3:$D$1402,2,FALSE) -> Unidad | D46: 2.6 | E46: =VLOOKUP(B46,'📦 Materiales'!$C$3:$E$1402,3,FALSE)/D46 -> 2007.3385 | G46: Esmalte sintético sobre madera satinado (3 manos) | H46: Pinturas Esmalte sintético s/ abertura. | I46: =VLOOKUP(H46,'🔨 Mano de Obra'!$H$4:$I$475,2,FALSE) -> 20480.23
A47: SOLERA 35MM (ML) | B47: Solera de 35mm x 2.60 mts. | C47: =VLOOKUP(B47,'📦 Materiales'!$C$3:$D$1402,2,FALSE) -> Unidad | D47: 2.6 | E47: =VLOOKUP(B47,'📦 Materiales'!$C$3:$E$1402,3,FALSE)/D47 -> 1872.3538 | G47: Esmalte sintético sobre metal brillante (3 manos) | H47: Pinturas Esmalte sintético s/ abertura. | I47: =VLOOKUP(H47,'🔨 Mano de Obra'!$H$4:$I$475,2,FALSE) -> 20480.23
A48: PERFIL Z BUÑA PERIMETRAL (ML/ML PM) | B48: Buña Perimetral Z x 2,60 mts. | C48: =VLOOKUP(B48,'📦 Materiales'!$C$3:$D$1402,2,FALSE) -> Unidad | D48: 2.6 | E48: =VLOOKUP(B48,'📦 Materiales'!$C$3:$E$1402,3,FALSE)/D48 -> 1760.4115 | G48: Esmalte sintético sobre metal satinado (3 manos) | H48: Pinturas Esmalte sintético s/ abertura. | I48: =VLOOKUP(H48,'🔨 Mano de Obra'!$H$4:$I$475,2,FALSE) -> 20480.23
A49: FIJADOR AL AGUA (LTS) | B49: Fijador-Sellador al Agua Alba, 20lts. | C49: =VLOOKUP(B49,'📦 Materiales'!$C$3:$D$1402,2,FALSE) -> Unidad | D49: 20 | E49: =VLOOKUP(B49,'📦 Materiales'!$C$3:$E$1402,3,FALSE)/D49 -> 10447.246 | G49: Revestimiento texturado exterior fino (2 mano) | H49: Revestimientos Texturado Texturado 1 Travertino/Rulato (Fino) | I49: =VLOOKUP(H49,'🔨 Mano de Obra'!$H$4:$I$475,2,FALSE) -> 16153.96
A50: ENDUIDO PLÁSTICO INTERIOR MATE (LTS) | B50: Enduido Interior Alba, 1kg | C50: =VLOOKUP(B50,'📦 Materiales'!$C$3:$D$1402,2,FALSE) -> Unidad | D50: 1 | E50: =VLOOKUP(B50,'📦 Materiales'!$C$3:$E$1402,3,FALSE)/D50 -> 15282.29 | G50: Revestimiento texturado exterior grueso (1 mano) | H50: Revestimientos Texturado Texturado 3 Travertino/Rulato (Grueso) | I50: =VLOOKUP(H50,'🔨 Mano de Obra'!$H$4:$I$475,2,FALSE) -> 21124.42
A51: RODILLO DE LANA (U) | B51: Rodillo Lana 22cm | C51: =VLOOKUP(B51,'📦 Materiales'!$C$3:$D$1402,2,FALSE) -> Unidad | D51: 1 | E51: =VLOOKUP(B51,'📦 Materiales'!$C$3:$E$1402,3,FALSE)/D51 -> 14383.33
A52: PINCEL N°20 (U) | B52: PINCEL N°20 (U) | C52: =VLOOKUP(B52,'📦 Materiales'!$C$3:$D$1402,2,FALSE) -> Unidad | D52: 1 | E52: =VLOOKUP(B52,'📦 Materiales'!$C$3:$E$1402,3,FALSE)/D52 -> 5000
A53: LÁTEX INTERIOR MATE (LTS) | B53: Latex Albalatex Design, 4lts. | C53: =VLOOKUP(B53,'📦 Materiales'!$C$3:$D$1402,2,FALSE) -> Unidad | D53: 4 | E53: =VLOOKUP(B53,'📦 Materiales'!$C$3:$E$1402,3,FALSE)/D53 -> 15126.945
A54: LÁTEX INTERIOR SATINADO (LTS) | B54: Latex Albalatex Design, 4lts. | C54: =VLOOKUP(B54,'📦 Materiales'!$C$3:$D$1402,2,FALSE) -> Unidad | D54: 4 | E54: =VLOOKUP(B54,'📦 Materiales'!$C$3:$E$1402,3,FALSE)/D54 -> 15126.945
A55: LÁTEX EXTERIOR MATE (LTS) | B55: Látex Profesional Exterior Alba | C55: =VLOOKUP(B55,'📦 Materiales'!$C$3:$D$1402,2,FALSE) -> Litro | D55: 1 | E55: =VLOOKUP(B55,'📦 Materiales'!$C$3:$E$1402,3,FALSE)/D55 -> 17080.23
A56: LÁTEX EXTERIOR SATINADO (LTS) | B56: Látex Profesional Exterior Alba | C56: =VLOOKUP(B56,'📦 Materiales'!$C$3:$D$1402,2,FALSE) -> Litro | D56: 1 | E56: =VLOOKUP(B56,'📦 Materiales'!$C$3:$E$1402,3,FALSE)/D56 -> 17080.23
A57: FIJADOR AL SOLVENTE (LTS) | B57: Fijador-Sellador al Agua Interior/Exterior Sinteplast | C57: =VLOOKUP(B57,'📦 Materiales'!$C$3:$D$1402,2,FALSE) -> Litro | D57: 1 | E57: =VLOOKUP(B57,'📦 Materiales'!$C$3:$E$1402,3,FALSE)/D57 -> 7551.26
A58: ESMALTE SINTÉTICO BRILLANTE (LTS) | B58: Esmalte Sintético Colorin, 4lts | C58: =VLOOKUP(B58,'📦 Materiales'!$C$3:$D$1402,2,FALSE) -> Unidad | D58: 4 | E58: =VLOOKUP(B58,'📦 Materiales'!$C$3:$E$1402,3,FALSE)/D58 -> 18428.67
A59: PINCEL N°5 (U) | B59: PINCEL N°5 (U) | C59: =VLOOKUP(B59,'📦 Materiales'!$C$3:$D$1402,2,FALSE) -> Unidad | D59: 1 | E59: =VLOOKUP(B59,'📦 Materiales'!$C$3:$E$1402,3,FALSE)/D59 -> 1200
A60: THINNER (LTS) | B60: Thinner Sinteplast, 1lt | C60: =VLOOKUP(B60,'📦 Materiales'!$C$3:$D$1402,2,FALSE) -> Unidad | D60: 1 | E60: =VLOOKUP(B60,'📦 Materiales'!$C$3:$E$1402,3,FALSE)/D60 -> 8630.01
A61: ESMALTE SINTÉTICO SATINADO (LTS) | B61: Esmalte Sintético Satinado Alba, 1lt | C61: =VLOOKUP(B61,'📦 Materiales'!$C$3:$D$1402,2,FALSE) -> Unidad | D61: 1 | E61: =VLOOKUP(B61,'📦 Materiales'!$C$3:$E$1402,3,FALSE)/D61 -> 25170.86
A62: CONVERTIDOR DE ÓXIDO (LTS) | B62: Convertidor de Oxido Blanco Venier, 1lt | C62: =VLOOKUP(B62,'📦 Materiales'!$C$3:$D$1402,2,FALSE) -> Unidad | D62: 1 | E62: =VLOOKUP(B62,'📦 Materiales'!$C$3:$E$1402,3,FALSE)/D62 -> 18878.12
... A64: REVESTIMIENTO TEXTURADO GRUESO (LTS) | B64: Revestimiento Tarquini Texturado Travertino/Rulato Grueso x 20kg. | C64: =VLOOKUP(B64,'📦 Materiales'!$C$3:$D$1402,2,FALSE) -> Unidad | D64: 20 | E64: =VLOOKUP(B64,'📦 Materiales'!$C$3:$E$1402,3,FALSE)/D64 -> 7379.4325

Sheet OPCIONES DE PISOS Y REVESTIMIEN
